Workbook
Name Slicer_listed_in: #N/A
Name Slicer_Platform: #N/A
Name Slicer_rating: #N/A
Name Slicer_type: #N/A

Sheet OTT_Data
A1: show_id | B1: type | C1: title | D1: director | E1: cast | F1: country | G1: date_added | H1: Date_Status | I1: release_year | J1: rating | K1: duration | L1: duration_movies | M1: duration_tv | N1: listed_in | O1: description | P1: Platform | Q1: Platform_Id | R1: Added_year | S1: Added_month | T1: content_age | U1: Duration_category | Z1: DATA QUALITY CHECK | AA1: Column1
A2: s4849P | B2: Movie | C2: Contract Lovers | D2: Francisco Marcano | E2: Franko Marcano, Arune Kital, Vincent Rivera | F2: Unknown | H2: Unknown | I2: 2021 | J2: 16+ | K2: 79 min | L2: 79 | M2: 0 | N2: Action | O2: After working undercover contracts on the Middle East and South America for a mercenary company he left the war life to start a new one in the city but instead he become a contract killer after his girlfriend dead | P2: Prime Video | Q2: 2 | R2: =IF(G2="","",YEAR(G2)) | S2: =IF(G2="","",TEXT(G2,"mmmm")) | T2: =IF(I2>=2020,"Recent",IF(I2>=2010,"Modern","Older")) -> Recent | U2: =IF(L2=0,"Not Applicable",IF(L2< 90,"Short",IF(L2<=120,"Medium","Long"))) -> Short | Z2: Total Records | AA2: =COUNTA(A2:A3001) -> 3000
A3: s516N | B3: TV Show | C3: Derry Girls | D3: Michael Lennox | E3: Saoirse-Monica Jackson, Nicola Coughlan, Louisa Harland, Jamie-Lee O'Donnell, Dylan Llewellyn, Tara Lynne O'Neill, Kathy Kiera Clarke, Tommy Tiernan, Ian McElhinney, Siobhan McSweeney | F3: United Kingdom | G3: 44383 | H3: Available | I3: 2019 | J3: TV-MA | K3: 2 Seasons | L3: 0 | M3: 2 | N3: British TV Shows | O3: Amidst the political conflict of Northern Ireland in the 1990s, five high school students square off with the universal challenges of being a teenager. | P3: Netflix | Q3: 1 | R3: =IF(G3="","",YEAR(G3)) -> 2021 | S3: =IF(G3="","",TEXT(G3,"mmmm")) -> July | T3: =IF(I3>=2020,"Recent",IF(I3>=2010,"Modern","Older")) -> Modern | U3: =IF(L3=0,"Not Applicable",IF(L3< 90,"Short",IF(L3<=120,"Medium","Long"))) -> Not Applicable | Z3: Missing Date Added | AA3: =COUNTBLANK(G2:G3001) -> 1554
A4: s1544P | B4: Movie | C4: My Name Was Bette: The Life and Death of an Alcoholic | D4: Sherri L. VandenAkker | E4: Bette VandenAkker, Sherri VandenAkker | F4: Unknown | H4: Unknown | I4: 2014 | J4: 16+ | K4: 60 min | L4: 60 | M4: 0 | N4: Documentaries | O4: A documentary about women's alcoholism chronicles the progression of the disease in Bette VandenAkker-a nurse, wife, and mother-who died in the fall of 2007. | P4: Prime Video | Q4: 2 | R4: =IF(G4="","",YEAR(G4)) | S4: =IF(G4="","",TEXT(G4,"mmmm")) | T4: =IF(I4>=2020,"Recent",IF(I4>=2010,"Modern","Older")) -> Modern | U4: =IF(L4=0,"Not Applicable",IF(L4< 90,"Short",IF(L4<=120,"Medium","Long"))) -> Short | Z4: Unknown Directors | AA4: =COUNTIF(D2:D3001,"Unknown") -> 674
A5: s295N | B5: Movie | C5: Takizawa Kabuki ZERO 2020 The Movie | D5: Hideaki Takizawa | E5: Hikaru Iwamoto, Tatsuya Fukazawa, Raul, Shota Watanabe, Koji Mukai, Ryohei Abe, Ren Meguro, Ryota Miyadate, Daisuke Sakuma, Arata Sato, Tatsuya Kageyama, Taiga Suzuki, Shunsuke Motoi, Taiga Tsubaki, Yuki Yokohara, Minato Matsui, Shosei Oda | F5: Unknown | G5: 44415 | H5: Available | I5: 2020 | J5: TV-PG | K5: 139 min | L5: 139 | M5: 0 | N5: International Movies | O5: Superstar Hideaki Takizawa reimagines his acclaimed kabuki production for the screen, featuring the dynamic talents of idol group Snow Man. | P5: Netflix | Q5: 1 | R5: =IF(G5="","",YEAR(G5)) -> 2021 | S5: =IF(G5="","",TEXT(G5,"mmmm")) -> August | T5: =IF(I5>=2020,"Recent",IF(I5>=2010,"Modern","Older")) -> Recent | U5: =IF(L5=0,"Not Applicable",IF(L5< 90,"Short",IF(L5<=120,"Medium","Long"))) -> Long | Z5: Unknown Ratings | AA5: =COUNTIF(J:J,"Not Rated") -> 114
A6: s7173P | B6: Movie | C6: Greener Mountains | D6: Lee Shallat Chemel | E6: Chris Heuisler, Kimberly McCullough, Brad Raider, Kevin Durand | F6: Unknown | H6: Unknown | I6: 2004 | J6: 13+ | K6: 89 min | L6: 89 | M6: 0 | N6: Comedy | O6: Greener Mountains is a family friendly, coming-of-age story about finding your place in the world. | P6: Prime Video | Q6: 2 | R6: =IF(G6="","",YEAR(G6)) | S6: =IF(G6="","",TEXT(G6,"mmmm")) | T6: =IF(I6>=2020,"Recent",IF(I6>=2010,"Modern","Older")) -> Older | U6: =IF(L6=0,"Not Applicable",IF(L6< 90,"Short",IF(L6<=120,"Medium","Long"))) -> Short | Z6: Movies | AA6: =COUNTIF(B2:B3001,"Movie") -> 2264
A7: s5366N | B7: TV Show | C7: Vexed | D7: Unknown | E7: Toby Stephens, Miranda Raison, Lucy Punch, Nick Dunning, Rory Kinnear, Ronny Jhutti, Roger Griffiths, Patrick Baladi | F7: United Kingdom | G7: 42948 | H7: Available | I7: 2012 | J7: TV-MA | K7: 2 Seasons | L7: 0 | M7: 2 | N7: British TV Shows | O7: Charming slacker DI Jack Armstrong and driven professional DI Kate Bishop try to solve crimes together without driving each other crazy. | P7: Netflix | Q7: 1 | R7: =IF(G7="","",YEAR(G7)) -> 2017 | S7: =IF(G7="","",TEXT(G7,"mmmm")) -> August | T7: =IF(I7>=2020,"Recent",IF(I7>=2010,"Modern","Older")) -> Modern | U7: =IF(L7=0,"Not Applicable",IF(L7< 90,"Short",IF(L7<=120,"Medium","Long"))) -> Not Applicable | Z7: TV Shows | AA7: =COUNTIF(B2:B3001,"TV Show") -> 736
A8: s4649N | B8: TV Show | C8: If I were an Animal | D8: Unknown | E8: Zachary Young, Fleur Delahunty | F8: Unknown | G8: 43354 | H8: Available | I8: 2018 | J8: TV-G | K8: 1 Season | L8: 0 | M8: 1 | N8: Docuseries | O8: Curious kids Emma and her big brother Tim observe different animals as they make their way through various life milestones, from birth to adulthood. | P8: Netflix | Q8: 1 | R8: =IF(G8="","",YEAR(G8)) -> 2018 | S8: =IF(G8="","",TEXT(G8,"mmmm")) -> September | T8: =IF(I8>=2020,"Recent",IF(I8>=2010,"Modern","Older")) -> Modern | U8: =IF(L8=0,"Not Applicable",IF(L8< 90,"Short",IF(L8<=120,"Medium","Long"))) -> Not Applicable
A9: s4636P | B9: Movie | C9: Learn to Read with Max the Glow Train! | D9: Not Available | E9: Unknown | F9: Unknown | H9: Unknown | I9: 2016 | J9: ALL | K9: 6 min | L9: 6 | M9: 0 | N9: Kids | O9: Max the Glow Train and his friends receive an unusual device called a Word Machine. After they read a word the machine makes a toy. Something happens and the machine goes out of control! | P9: Prime Video | Q9: 2 | R9: =IF(G9="","",YEAR(G9)) | S9: =IF(G9="","",TEXT(G9,"mmmm")) | T9: =IF(I9>=2020,"Recent",IF(I9>=2010,"Modern","Older")) -> Modern | U9: =IF(L9=0,"Not Applicable",IF(L9< 90,"Short",IF(L9<=120,"Medium","Long"))) -> Short
A10: s2288N | B10: Movie | C10: Queen | D10: Vikas Bahl | E10: Kangana Ranaut, Rajkummar Rao, Lisa Haydon, Mish Boyko, Jeffrey Chee Eng Ho, Marco Canadea, Sabeeka Imam, Yogendra Tikku | F10: India | G10: 44017 | H10: Available | I10: 2014 | J10: TV-MA | K10: 138 min | L10: 138 | M10: 0 | N10: Comedy | O10: Dumped by her fiancé, a sheltered young woman decides to go on her honeymoon to Europe alone, embarking on an exhilarating journey of self-discovery. | P10: Netflix | Q10: 1 | R10: =IF(G10="","",YEAR(G10)) -> 2020 | S10: =IF(G10="","",TEXT(G10,"mmmm")) -> July | T10: =IF(I10>=2020,"Recent",IF(I10>=2010,"Modern","Older")) -> Modern | U10: =IF(L10=0,"Not Applicable",IF(L10< 90,"Short",IF(L10<=120,"Medium","Long"))) -> Long
A11: s4974P | B11: Movie | C11: Hoop Soldiers | D11: Chris Rogers | E11: Tank Jones, Cassandra King | F11: Unknown | H11: Unknown | I11: 2001 | J11: R | K11: 99 min | L11: 99 | M11: 0 | N11: Action | O11: While investigating her brother's death, a lawyer uncovers an illegal basketball league where the games are often fatal. | P11: Prime Video | Q11: 2 | R11: =IF(G11="","",YEAR(G11)) | S11: =IF(G11="","",TEXT(G11,"mmmm")) | T11: =IF(I11>=2020,"Recent",IF(I11>=2010,"Modern","Older")) -> Older | U11: =IF(L11=0,"Not Applicable",IF(L11< 90,"Short",IF(L11<=120,"Medium","Long"))) -> Medium
A12: s1211P | B12: Movie | C12: Rampage | D12: Uwe Boll | E12: Brendan Fletcher, Shaun Sipos, Michael ParÃ© | F12: Unknown | H12: Unknown | I12: 2011 | J12: R | K12: 85 min | L12: 85 | M12: 0 | N12: Action | O12: The boredom of small town life is eating Bill Williamson alive. Feeling constrained and claustrophobic in the meaningless drudgery of everyday life and helpless against overwhelming global dissolution, Bill (Brendan Fletcher) begins a descent into madness. His shockingly violent plan will shake the very foundations of society by painting the streets red with blood. | P12: Prime Video | Q12: 2 | R12: =IF(G12="","",YEAR(G12)) | S12: =IF(G12="","",TEXT(G12,"mmmm")) | T12: =IF(I12>=2020,"Recent",IF(I12>=2010,"Modern","Older")) -> Modern | U12: =IF(L12=0,"Not Applicable",IF(L12< 90,"Short",IF(L12<=120,"Medium","Long"))) -> Short
A13: s845N | B13: Movie | C13: Nail Bomber: Manhunt | D13: Daniel Vernon | E13: Unknown | F13: Unknown | G13: 44342 | H13: Available | I13: 2021 | J13: TV-MA | K13: 73 min | L13: 73 | M13: 0 | N13: Documentaries | O13: This documentary examines the 1999 London bombings that targeted Black, Bangladeshi and gay communities, and the race to find the far-right perpetrator. | P13: Netflix | Q13: 1 | R13: =IF(G13="","",YEAR(G13)) -> 2021 | S13: =IF(G13="","",TEXT(G13,"mmmm")) -> May | T13: =IF(I13>=2020,"Recent",IF(I13>=2010,"Modern","Older")) -> Recent | U13: =IF(L13=0,"Not Applicable",IF(L13< 90,"Short",IF(L13<=120,"Medium","Long"))) -> Short
A14: s60N | B14: Movie | C14: Naruto Shippuden: The Movie | D14: Hajime Kamegaki | E14: Junko Takeuchi, Chie Nakamura, Yoichi Masukawa, Koichi Tochika, Ayumi Fujimura, Keisuke Oda, Daisuke Kishio, Fumiko Orikasa, Hidetoshi Nakamura, Tetsuya Kakihara, Kisho Taniyama, Miyuki Sawashiro, Katsuyuki Konishi, Masako Katsuki, Keiko Nemoto, Masashi Ebara, Kazuhiko Inoue, Showtaro Morikubo, Romi Park, Daisuke Ono, Seizo Kato | F14: Japan | G14: 44454 | H14: Available | I14: 2007 | J14: TV-PG | K14: 95 min | L14: 95 | M14: 0 | N14: Action & Adventure | O14: The adventures of adolescent ninja Naruto Uzumaki continue as he's tasked with protecting a priestess from a demon – but to do so, he must die. | P14: Netflix | Q14: 1 | R14: =IF(G14="","",YEAR(G14)) -> 2021 | S14: =IF(G14="","",TEXT(G14,"mmmm")) -> September | T14: =IF(I14>=2020,"Recent",IF(I14>=2010,"Modern","Older")) -> Older | U14: =IF(L14=0,"Not Applicable",IF(L14< 90,"Short",IF(L14<=120,"Medium","Long"))) -> Medium
A15: s1092P | B15: Movie | C15: Sawan Ko Aane Do | D15: Kanak Mishra | E15: Arun Govil, Zarina Wahab, Amrish Puri, Rita Bhaduri, Yunus Parvez, Leela Mishra | F15: Unknown | H15: Unknown | I15: 1979 | J15: ALL | K15: 153 min | L15: 153 | M15: 0 | N15: Drama | O15: Sawan Ko Aane Do is a 1979 Rajshri Productions Hindi movie produced by Tarachand Barjatya and directed by Kanak Mishra. It's a story about Birju, a poor villager who wants to marry the headman's daughter, her father gets furious and sends her to the city. Years later, Birju becomes a successful singer and returns to seek his approval. | P15: Prime Video | Q15: 2 | R15: =IF(G15="","",YEAR(G15)) | S15: =IF(G15="","",TEXT(G15,"mmmm")) | T15: =IF(I15>=2020,"Recent",IF(I15>=2010,"Modern","Older")) -> Older | U15: =IF(L15=0,"Not Applicable",IF(L15< 90,"Short",IF(L15<=120,"Medium","Long"))) -> Long
A16: s7472P | B16: TV Show | C16: Alien Extinction | D16: Unknown | E16: Geovanni Molina | F16: Unknown | H16: Unknown | I16: 2020 | J16: 16+ | K16: 1 Season | L16: 0 | M16: 1 | N16: Action | O16: Earth has encountered an Alien that his sole mission is to destroy all human life . Two galactic bounty have been sent from another planet to stop the extinction of man before its to late. | P16: Prime Video | Q16: 2 | R16: =IF(G16="","",YEAR(G16)) | S16: =IF(G16="","",TEXT(G16,"mmmm")) | T16: =IF(I16>=2020,"Recent",IF(I16>=2010,"Modern","Older")) -> Recent | U16: =IF(L16=0,"Not Applicable",IF(L16< 90,"Short",IF(L16<=120,"Medium","Long"))) -> Not Applicable
A17: s1000N | B17: Movie | C17: Stowaway | D17: Joe Penna | E17: Anna Kendrick, Toni Collette, Daniel Dae Kim, Shamier Anderson | F17: Germany, United States | G17: 44308 | H17: Available | I17: 2021 | J17: TV-MA | K17: 116 min | L17: 116 | M17: 0 | N17: Drama | O17: A three-person crew on a mission to Mars faces an impossible choice when an unplanned passenger jeopardizes the lives of everyone on board. | P17: Netflix | Q17: 1 | R17: =IF(G17="","",YEAR(G17)) -> 2021 | S17: =IF(G17="","",TEXT(G17,"mmmm")) -> April | T17: =IF(I17>=2020,"Recent",IF(I17>=2010,"Modern","Older")) -> Recent | U17: =IF(L17=0,"Not Applicable",IF(L17< 90,"Short",IF(L17<=120,"Medium","Long"))) -> Medium
A18: s3950N | B18: TV Show | C18: Tango | D18: Unknown | E18: Bassel Khayyat, Daniella Rahme, Bassam Moughneih, Dana Mardini, Youssef Haddad, Talal Jarday, Sameera Barody | F18: Lebanon | G18: 43558 | H18: Available | I18: 2018 | J18: TV-14 | K18: 1 Season | L18: 0 | M18: 1 | N18: International TV Shows | O18: Shocking secrets begin to unravel when the aftermath of a car crash leaves four best friends questioning the truth of their relationships. | P18: Netflix | Q18: 1 | R18: =IF(G18="","",YEAR(G18)) -> 2019 | S18: =IF(G18="","",TEXT(G18,"mmmm")) -> April | T18: =IF(I18>=2020,"Recent",IF(I18>=2010,"Modern","Older")) -> Modern | U18: =IF(L18=0,"Not Applicable",IF(L18< 90,"Short",IF(L18<=120,"Medium","Long"))) -> Not Applicable
A19: s7940N | B19: Movie | C19: Sarvopari Palakkaran | D19: Venugopan | E19: Anoop Menon, Alencier Ley Lopez, Balu Varghese, Aparna Balamurali, Anu Sithara, Gayathri Arun, Nandu, Chali Pala | F19: India | G19: 43282 | H19: Available | I19: 2017 | J19: TV-14 | K19: 133 min | L19: 133 | M19: 0 | N19: Drama | O19: In the course of a human trafficking investigation, a conservative cop crosses paths with an artist-activist in a clash of worldviews. | P19: Netflix | Q19: 1 | R19: =IF(G19="","",YEAR(G19)) -> 2018 | S19: =IF(G19="","",TEXT(G19,"mmmm")) -> July | T19: =IF(I19>=2020,"Recent",IF(I19>=2010,"Modern","Older")) -> Modern | U19: =IF(L19=0,"Not Applicable",IF(L19< 90,"Short",IF(L19<=120,"Medium","Long"))) -> Long
A20: s1029P | B20: TV Show | C20: Shepherd | D20: Unknown | E20: Lance E. Nichols, Kelvin Harrison Jr., Alicia Davis Johnson, Chelsea Bryan | F20: Unknown | H20: Unknown | I20: 2021 | J20: 13+ | K20: 1 Season | L20: 0 | M20: 1 | N20: Drama | O20: Veteran actor Lance Nichols (Into the Badlands, House of Cards) heads this New Orleans-based cast as Father Joseph, a Catholic priest with a violent past who wages war with a dangerous drug lord after an attack at his church on Christmas Eve. Kelvin Harrison Jr. (Luce, Waves) co-stars as Will, a former altar boy turned drug dealer who gets caught up in Father Joseph's pursuit for justice. | P20: Prime Video | Q20: 2 | R20: =IF(G20="","",YEAR(G20)) | S20: =IF(G20="","",TEXT(G20,"mmmm")) | T20: =IF(I20>=2020,"Recent",IF(I20>=2010,"Modern","Older")) -> Recent | U20: =IF(L20=0,"Not Applicable",IF(L20< 90,"Short",IF(L20<=120,"Medium","Long"))) -> Not Applicable
A21: s1170P | B21: Movie | C21: Rhythm In the Clouds | D21: John H. Auer | E21: Patricia Ellis, Warren Hull, William Newell, Richard Carle, Zeffie Tilbury, Charles Judels, Robert Paige, Joyce Compton | F21: Unknown | H21: Unknown | I21: 1937 | J21: PG | K21: 53 min | L21: 53 | M21: 0 | N21: Arts | O21: Struggling songwriter Judy Walker talks her way into the apartment of a famous composer, and finds that he's on vacation. Homeless and without any money, she decides to stay at his place until his return, making use of all his belongings, and spreading the word that she is the composer's collaborator. She writes a song, wtih the composer listed as the co-writer, which becomes a big radio hit. The famous composer returns, and screwball comedy ensues. | P21: Prime Video | Q21: 2 | R21: =IF(G21="","",YEAR(G21)) | S21: =IF(G21="","",TEXT(G21,"mmmm")) | T21: =IF(I21>=2020,"Recent",IF(I21>=2010,"Modern","Older")) -> Older | U21: =IF(L21=0,"Not Applicable",IF(L21< 90,"Short",IF(L21<=120,"Medium","Long"))) -> Short
A22: s2057N | B22: Movie | C22: Hotel for Dogs | D22: Thor Freudenthal | E22: Emma Roberts, Jake T. Austin, Kyla Pratt, Lisa Kudrow, Kevin Dillon, Don Cheadle, Johnny Simmons, Troy Gentile, Eric Edelstein, Robinne Lee, Ajay Naidu | F22: Germany, United States | G22: 44076 | H22: Available | I22: 2009 | J22: PG | K22: 101 min | L22: 101 | M22: 0 | N22: Kids & Family Movies | O22: Placed in a foster home that doesn't allow pets, 16-year-old Andi and her younger brother Bruce turn an abandoned hotel into a home for their dog. | P22: Netflix | Q22: 1 | R22: =IF(G22="","",YEAR(G22)) -> 2020 | S22: =IF(G22="","",TEXT(G22,"mmmm")) -> September | T22: =IF(I22>=2020,"Recent",IF(I22>=2010,"Modern","Older")) -> Older | U22: =IF(L22=0,"Not Applicable",IF(L22< 90,"Short",IF(L22<=120,"Medium","Long"))) -> Medium
A23: s5309N | B23: Movie | C23: Rocco | D23: Thierry Demaizière, Alban Teurlai | E23: Rocco Siffredi | F23: France | G23: 42979 | H23: Available | I23: 2016 | J23: TV-MA | K23: 103 min | L23: 103 | M23: 0 | N23: Documentaries | O23: Italian porn star Rocco Siffredi is showcased in this documentary that shadows the legendary performer during his final year in front of the camera. | P23: Netflix | Q23: 1 | R23: =IF(G23="","",YEAR(G23)) -> 2017 | S23: =IF(G23="","",TEXT(G23,"mmmm")) -> September | T23: =IF(I23>=2020,"Recent",IF(I23>=2010,"Modern","Older")) -> Modern | U23: =IF(L23=0,"Not Applicable",IF(L23< 90,"Short",IF(L23<=120,"Medium","Long"))) -> Medium
A24: s6063N | B24: Movie | C24: A Walk to Remember | D24: Adam Shankman | E24: Mandy Moore, Shane West, Peter Coyote, Daryl Hannah, Lauren German, Clayne Crawford, Al Thompson | F24: United States | G24: 44013 | H24: Available | I24: 2002 | J24: PG | K24: 102 min | L24: 102 | M24: 0 | N24: Drama | O24: When bad boy Landon is cast opposite campus bookworm Jamie in a high school play, romance blooms — until tragedy threatens to tear them apart. | P24: Netflix | Q24: 1 | R24: =IF(G24="","",YEAR(G24)) -> 2020 | S24: =IF(G24="","",TEXT(G24,"mmmm")) -> July | T24: =IF(I24>=2020,"Recent",IF(I24>=2010,"Modern","Older")) -> Older | U24: =IF(L24=0,"Not Applicable",IF(L24< 90,"Short",IF(L24<=120,"Medium","Long"))) -> Medium
A25: s3750P | B25: Movie | C25: The Amazing Mr. Blunden | D25: Lionel Jeffries | E25: Laurence Naismith, Lynne Frederick, Gary Miller | F25: Unknown | H25: Unknown | I25: 1963 | J25: 13+ | K25: 84 min | L25: 84 | M25: 0 | N25: Fantasy | O25: The mysterious solicitor, Mr. Blunden, visits the near-destitute Mrs. Allen and her young Kids in her squalid, tiny Camden Town flat, and makes her an offer she can't refuse. The family becomes the housekeepers to a derelict country mansion in the charge of the solicitors. | P25: Prime Video | Q25: 2 | R25: =IF(G25="","",YEAR(G25)) | S25: =IF(G25="","",TEXT(G25,"mmmm")) | T25: =IF(I25>=2020,"Recent",IF(I25>=2010,"Modern","Older")) -> Older | U25: =IF(L25=0,"Not Applicable",IF(L25< 90,"Short",IF(L25<=120,"Medium","Long"))) -> Short
A26: s3246N | B26: TV Show | C26: Singapore Social | D26: Unknown | E26: Nicole Ong, Mae Tan, Sukki Singapora, Vinny Sharp, Paul Foster, Tabitha Nauser | F26: Singapore, United States | G26: 43791 | H26: Available | I26: 2019 | J26: TV-MA | K26: 1 Season | L26: 0 | M26: 1 | N26: International TV Shows | O26: Peer into the lives of young Singaporeans as they defy expectations and traverse the tricky terrain of career, romance and family. | P26: Netflix | Q26: 1 | R26: =IF(G26="","",YEAR(G26)) -> 2019 | S26: =IF(G26="","",TEXT(G26,"mmmm")) -> November | T26: =IF(I26>=2020,"Recent",IF(I26>=2010,"Modern","Older")) -> Modern | U26: =IF(L26=0,"Not Applicable",IF(L26< 90,"Short",IF(L26<=120,"Medium","Long"))) -> Not Applicable
A27: s5863P | B27: TV Show | C27: Da Kink In My Hair | D27: Unknown | E27: Ordena Stephens, Trey Anthony, Ngozi Paul | F27: Unknown | H27: Unknown | I27: 2009 | J27: TV-14 | K27: 2 Seasons | L27: 0 | M27: 2 | N27: Comedy | O27: Novelette's personal life picks up where it left off in season one - complicated! She is romantically involved with Richard, but his ex-wife and family get in the way. Making matters worse, Dre's father, Cedric, re-enters her life. As Novelette tries to untangle the webs in her personal life, she still has a shop to run and a family to look over. | P27: Prime Video | Q27: 2 | R27: =IF(G27="","",YEAR(G27)) | S27: =IF(G27="","",TEXT(G27,"mmmm")) | T27: =IF(I27>=2020,"Recent",IF(I27>=2010,"Modern","Older")) -> Older | U27: =IF(L27=0,"Not Applicable",IF(L27< 90,"Short",IF(L27<=120,"Medium","Long"))) -> Not Applicable
A28: s9173P | B28: Movie | C28: Je Suis A Stand-Up: Eddie Izzard Abroad | D28: Paul Tickell | E28: Eddie Izzard | F28: Unknown | H28: Unknown | I28: 1996 | J28: 18+ | K28: 48 min | L28: 48 | M28: 0 | N28: Arts | O28: BBC2 documentary of Eddie Izzard's first foray into world touring. Beginning in her "hometown" of Eastbourne and and culminating in his month long show in the East village of New York, Izzard travels to Paris (her first, unsuccessful French language show,) Copenhagen, Reykjavik, and Stockholm. | P28: Prime Video | Q28: 2 | R28: =IF(G28="","",YEAR(G28)) | S28: =IF(G28="","",TEXT(G28,"mmmm")) | T28: =IF(I28>=2020,"Recent",IF(I28>=2010,"Modern","Older")) -> Older | U28: =IF(L28=0,"Not Applicable",IF(L28< 90,"Short",IF(L28<=120,"Medium","Long"))) -> Short
A29: s2642N | B29: TV Show | C29: DreamWorks Spooky Stories: Volume 2 | D29: Unknown | E29: Seth Rogen, Will Arnett, Hugh Laurie, Will Ferrell, David Cross, Sean Bishop, Kiefer Sutherland, Cody Cameron, Aron Warner | F29: Unknown | G29: 43945 | H29: Available | I29: 2011 | J29: TV-PG | K29: 1 Season | L29: 0 | M29: 1 | N29: Kids | O29: The Shrek characters parody the music video "Thriller"; B.O.B. and pals battle zombie carrots; and Megamind faces the effects of the Button of Doom. | P29: Netflix | Q29: 1 | R29: =IF(G29="","",YEAR(G29)) -> 2020 | S29: =IF(G29="","",TEXT(G29,"mmmm")) -> April | T29: =IF(I29>=2020,"Recent",IF(I29>=2010,"Modern","Older")) -> Modern | U29: =IF(L29=0,"Not Applicable",IF(L29< 90,"Short",IF(L29<=120,"Medium","Long"))) -> Not Applicable
A30: s5912N | B30: Movie | C30: Jen Kirkman: I'm Gonna Die Alone (And I Feel Fine) | D30: Lance Bangs | E30: Jen Kirkman | F30: United States | G30: 42146 | H30: Available | I30: 2015 | J30: TV-MA | K30: 78 min | L30: 78 | M30: 0 | N30: Stand-Up Comedy | O30: Jen Kirkman delivers some sharp, hilarious truths about divorce, kids, sex and turning 40 in this Netflix original comedy special. | P30: Netflix | Q30: 1 | R30: =IF(G30="","",YEAR(G30)) -> 2015 | S30: =IF(G30="","",TEXT(G30,"mmmm")) -> May | T30: =IF(I30>=2020,"Recent",IF(I30>=2010,"Modern","Older")) -> Modern | U30: =IF(L30=0,"Not Applicable",IF(L30< 90,"Short",IF(L30<=120,"Medium","Long"))) -> Short
A31: s6394N | B31: TV Show | C31: Burnistoun | D31: Unknown | E31: Iain Connell, Robert Florence, Kirsty Strain, Richard Rankin, Allan Miller, Louise Stewart | F31: United Kingdom | G31: 43739 | H31: Available | I31: 2012 | J31: TV-MA | K31: 2 Seasons | L31: 0 | M31: 2 | N31: British TV Shows | O31: This sketch series focuses on the eccentric characters in a small Scottish town, including bumbling cops, "DJ Jesus" and a disgruntled serial killer. | P31: Netflix | Q31: 1 | R31: =IF(G31="","",YEAR(G31)) -> 2019 | S31: =IF(G31="","",TEXT(G31,"mmmm")) -> October | T31: =IF(I31>=2020,"Recent",IF(I31>=2010,"Modern","Older")) -> Modern | U31: =IF(L31=0,"Not Applicable",IF(L31< 90,"Short",IF(L31<=120,"Medium","Long"))) -> Not Applicable
A32: s3839N | B32: TV Show | C32: The Mechanism | D32: Unknown | E32: Selton Mello, Caroline Abras, Enrique Diaz, Antonio Saboia, Lee Taylor, Otto Jr., Leonardo Medeiros, Osvaldo Mil, Jonathan Haagensen, Giulio Lopes, Susana Ribeiro | F32: Brazil | G32: 43595 | H32: Available | I32: 2019 | J32: TV-MA | K32: 2 Seasons | L32: 0 | M32: 2 | N32: Crime TV Shows | O32: A scandal erupts in Brazil during an investigation of alleged government corruption via oil and construction companies. Loosely inspired by true events. | P32: Netflix | Q32: 1 | R32: =IF(G32="","",YEAR(G32)) -> 2019 | S32: =IF(G32="","",TEXT(G32,"mmmm")) -> May | T32: =IF(I32>=2020,"Recent",IF(I32>=2010,"Modern","Older")) -> Modern | U32: =IF(L32=0,"Not Applicable",IF(L32< 90,"Short",IF(L32<=120,"Medium","Long"))) -> Not Applicable
A33: s9641P | B33: Movie | C33: Meet the Spartans (Uncut) | D33: Jason Friedberg, Aaron Setzer | E33: Sean Maguire, Carmen Electra, Ken Davitian, Kevin Sorbo, Diedrich Bader, Method Man, Jareb Dauplaise, Travis Van Winkle, Phil Morris, Jim Piddock, Nicole Parker, Ike Barinholtz, Crista Flanagan, Hunter Clary, Emily Wilson, Thomas McKenna, Tiffany Haddish, Willie Macc, Kenny Yates, John Di Domenico, Christopher Lett, Jenny Costa, Belinda Waymouth, Jesse Lewis IV, Zachary Dylan Smith, Ryan Fraley, Tiffany Claus, Nick Steele, Jim Nieb, Dean Cochran, Nate Haden, Tony Yalda, Chris Crocker | F33: United States | H33: Unknown | I33: 2008 | J33: 18+ | K33: 86 min | L33: 86 | M33: 0 | N33: Comedy | O33: From the creators of Scary Movie and Date Movie comes this tongue-in-cheek parody of the sword-and-sandal epics. The heroic Leonidas, armed with nothing by leather underwear and a cape, leads a ragtag group of 13 - count 'em, 13! ? Spartans to defend their homeland against the invading Persians (whose ranks include Ghost Rider, Rocky Balboa, the Transformers, and a hunchbacked Paris Hilton... no one is safe when the Spartans take on the biggest icons in pop culture). | P33: Prime Video | Q33: 2 | R33: =IF(G33="","",YEAR(G33)) | S33: =IF(G33="","",TEXT(G33,"mmmm")) | T33: =IF(I33>=2020,"Recent",IF(I33>=2010,"Modern","Older")) -> Older | U33: =IF(L33=0,"Not Applicable",IF(L33< 90,"Short",IF(L33<=120,"Medium","Long"))) -> Short
A34: s5487N | B34: Movie | C34: The Devil's Mistress | D34: Filip Renc | E34: Tatiana Pauhofová, Karl Markovics, Gedeon Burkhard, Simona Stasová, Martin Huba, Pavel Kríz, Zdenka Procházková, Anna Fialová, Lenka Vlasáková, Jirí Mádl | F34: Czech Republic, Slovakia | G34: 42870 | H34: Available | I34: 2016 | J34: TV-MA | K34: 110 min | L34: 110 | M34: 0 | N34: Drama | O34: Before the dawn of World War II, an ambitious actress pursues her dreams in Berlin. But her plans derail when she becomes Joseph Goebbels’ mistress. | P34: Netflix | Q34: 1 | R34: =IF(G34="","",YEAR(G34)) -> 2017 | S34: =IF(G34="","",TEXT(G34,"mmmm")) -> May | T34: =IF(I34>=2020,"Recent",IF(I34>=2010,"Modern","Older")) -> Modern | U34: =IF(L34=0,"Not Applicable",IF(L34< 90,"Short",IF(L34<=120,"Medium","Long"))) -> Medium
A35: s1013P | B35: TV Show | C35: Sigmund and the Sea Monsters | D35: Unknown | E35: Rebecca Bloom, David Arquette, Solomon Stewart, Mark Povinelli, Eileen Oâ€™Connell, Drew Massey, Michael Oosterom, Victor Yerrid, Meegan Godfrey, David Crespin, Kyle Harrison Breitkopf | F35: Unknown | H35: Unknown | I35: 2017 | J35: 7+ | K35: 1 Season | L35: 0 | M35: 1 | N35: Kids | O35: Brothers Johnny and Scotty find Sigmund, a sea monster, on the beach and bring him home to their clubhouse. They become fast friends, but when a monster hunter, Capt. Barnabas (David Arquette), finds out, the kids have to scramble to keep Sigmund hidden. Worse still, Sigmund's brothers Blurp and Slurp don't like humans. Against all odds, can they still have an endless summer of fun? | P35: Prime Video | Q35: 2 | R35: =IF(G35="","",YEAR(G35)) | S35: =IF(G35="","",TEXT(G35,"mmmm")) | T35: =IF(I35>=2020,"Recent",IF(I35>=2010,"Modern","Older")) -> Modern | U35: =IF(L35=0,"Not Applicable",IF(L35< 90,"Short",IF(L35<=120,"Medium","Long"))) -> Not Applicable
A36: s4485N | B36: Movie | C36: Scorpion King 5: Book of Souls | D36: Don Michael Paul | E36: Zach McGowan, Pearl Thusi, Nathan Jones, Peter Mensah, Katy Louise Saunders, Mayling Ng, Howard Charles, Inge Beckmann | F36: United States | G36: 43396 | H36: Available | I36: 2018 | J36: PG-13 | K36: 102 min | L36: 102 | M36: 0 | N36: Action & Adventure | O36: The Scorpion King joins forces with a Nubian princess in an all-or-nothing fight to stop a warlord from claiming the souls of the vanquished. | P36: Netflix | Q36: 1 | R36: =IF(G36="","",YEAR(G36)) -> 2018 | S36: =IF(G36="","",TEXT(G36,"mmmm")) -> October | T36: =IF(I36>=2020,"Recent",IF(I36>=2010,"Modern","Older")) -> Modern | U36: =IF(L36=0,"Not Applicable",IF(L36< 90,"Short",IF(L36<=120,"Medium","Long"))) -> Medium
A37: s7735N | B37: Movie | C37: Phantom Boy | D37: Jean-Loup Felicioli, Alain Gagnol | E37: Marcus D'Angelo, Vincent D'Onofrio, Fred Armisen, Jared Padalecki, Joey Camen, Brian T. Delaney, Melissa Disney, Bill Lobley, Amanda Céline Miller, Dana Snyder, Stephanie Sheh | F37: France, Belgium | G37: 43009 | H37: Available | I37: 2015 | J37: PG | K37: 85 min | L37: 85 | M37: 0 | N37: Action & Adventure | O37: A boy whose illness allows him to float outside his body uses his newfound skill to help a cop take on a madman who's terrorizing New York City. | P37: Netflix | Q37: 1 | R37: =IF(G37="","",YEAR(G37)) -> 2017 | S37: =IF(G37="","",TEXT(G37,"mmmm")) -> October | T37: =IF(I37>=2020,"Recent",IF(I37>=2010,"Modern","Older")) -> Modern | U37: =IF(L37=0,"Not Applicable",IF(L37< 90,"Short",IF(L37<=120,"Medium","Long"))) -> Short
A38: s8559P | B38: Movie | C38: Chicago Massacre | D38: Michael Feifer | E38: Corin Nemec, Amy Lyndon | F38: Unknown | H38: Unknown | I38: 2007 | J38: R | K38: 92 min | L38: 92 | M38: 0 | N38: Documentaries | O38: A film based on the notorious mass killer Richard Speck, who systematically tortured, raped and murdered a group of student nurses from South Chicago Community Hospital in 1966. | P38: Prime Video | Q38: 2 | R38: =IF(G38="","",YEAR(G38)) | S38: =IF(G38="","",TEXT(G38,"mmmm")) | T38: =IF(I38>=2020,"Recent",IF(I38>=2010,"Modern","Older")) -> Older | U38: =IF(L38=0,"Not Applicable",IF(L38< 90,"Short",IF(L38<=120,"Medium","Long"))) -> Medium
A39: s2934N | B39: Movie | C39: Polaroid | D39: Lars Klevberg | E39: Kathryn Prescott, Mitch Pileggi, Grace Zabriskie, Tyler Young, Samantha Logan, Javier Botet, Katie Stevens, Madelaine Petsch, Priscilla Quintana, Davi Santos, Keenan Tracey | F39: United States, Norway, Canada | G39: 43870 | H39: Available | I39: 2019 | J39: PG-13 | K39: 88 min | L39: 88 | M39: 0 | N39: Horror | O39: A teen's discovery of a vintage Polaroid camera develops into a darker tale when she finds that whoever takes their photo with it dies soon afterward. | P39: Netflix | Q39: 1 | R39: =IF(G39="","",YEAR(G39)) -> 2020 | S39: =IF(G39="","",TEXT(G39,"mmmm")) -> February | T39: =IF(I39>=2020,"Recent",IF(I39>=2010,"Modern","Older")) -> Modern | U39: =IF(L39=0,"Not Applicable",IF(L39< 90,"Short",IF(L39<=120,"Medium","Long"))) -> Short
A40: s1651N | B40: Movie | C40: Shawn Mendes: Live in Concert | D40: Paul Dugdale | E40: Shawn Mendes | F40: United Kingdom, United States | G40: 44160 | H40: Available | I40: 2020 | J40: TV-PG | K40: 87 min | L40: 87 | M40: 0 | N40: Music & Musicals | O40: In his hometown of Toronto, Shawn Mendes pours his heart out on stage with a live performance in a stadium packed with adoring fans. | P40: Netflix | Q40: 1 | R40: =IF(G40="","",YEAR(G40)) -> 2020 | S40: =IF(G40="","",TEXT(G40,"mmmm")) -> November | T40: =IF(I40>=2020,"Recent",IF(I40>=2010,"Modern","Older")) -> Recent | U40: =IF(L40=0,"Not Applicable",IF(L40< 90,"Short",IF(L40<=120,"Medium","Long"))) -> Short
A41: s648N | B41: TV Show | C41: The Parisian Agency: Exclusive Properties | D41: Unknown | E41: Olivier Kretz, Sandrine Kretz, Valentin Kretz, Martin Kretz, Louis Kretz | F41: Unknown | G41: 44370 | H41: Available | I41: 2021 | J41: TV-G | K41: 1 Season | L41: 0 | M41: 1 | N41: Reality | O41: This reality series follows the Kretz family and their luxury property business as they help clients buy and sell fabulous homes in France and abroad. | P41: Netflix | Q41: 1 | R41: =IF(G41="","",YEAR(G41)) -> 2021 | S41: =IF(G41="","",TEXT(G41,"mmmm")) -> June | T41: =IF(I41>=2020,"Recent",IF(I41>=2010,"Modern","Older")) -> Recent | U41: =IF(L41=0,"Not Applicable",IF(L41< 90,"Short",IF(L41<=120,"Medium","Long"))) -> Not Applicable
A42: s1803N | B42: Movie | C42: Shattered Memories | D42: Chris Sivertson | E42: Elizabeth Bogush, Brad Schmidt, Sarah Lind, Eddie Kaye Thomas, Phillip Boyd, Victoria Barabas, Mark Famiglietti, Walker Borba, Meg DeLacy | F42: United States | G42: 44127 | H42: Available | I42: 2018 | J42: TV-14 | K42: 86 min | L42: 86 | M42: 0 | N42: Drama | O42: When her former lover's mysteriously murdered, a woman must clear her name – and avoid the killer. | P42: Netflix | Q42: 1 | R42: =IF(G42="","",YEAR(G42)) -> 2020 | S42: =IF(G42="","",TEXT(G42,"mmmm")) -> October | T42: =IF(I42>=2020,"Recent",IF(I42>=2010,"Modern","Older")) -> Modern | U42: =IF(L42=0,"Not Applicable",IF(L42< 90,"Short",IF(L42<=120,"Medium","Long"))) -> Short
A43: s2476N | B43: Movie | C43: Si Doel the Movie 3 | D43: Rano Karno | E43: Rano Karno, Cornelia Agatha, Maudy Koesnaedi, Suty Karno, Mandra Naih, Aminah Tjendrakasih, Rey Bong, Akhmad Zulhoir Mardia | F43: Indonesia | G43: 43974 | H43: Available | I43: 2020 | J43: TV-G | K43: 93 min | L43: 93 | M43: 0 | N43: Drama | O43: Torn between reuniting with one family and leaving another behind, Doel must choose between the two women he loves. | P43: Netflix | Q43: 1 | R43: =IF(G43="","",YEAR(G43)) -> 2020 | S43: =IF(G43="","",TEXT(G43,"mmmm")) -> May | T43: =IF(I43>=2020,"Recent",IF(I43>=2010,"Modern","Older")) -> Recent | U43: =IF(L43=0,"Not Applicable",IF(L43< 90,"Short",IF(L43<=120,"Medium","Long"))) -> Medium
A44: s165N | B44: Movie | C44: Mystery Men | D44: Kinka Usher | E44: Ben Stiller, Hank Azaria, William H. Macy, Janeane Garofalo, Kel Mitchell, Paul Reubens, Wes Studi, Greg Kinnear, Geoffrey Rush, Lena Olin, Eddie Izzard, Artie Lange, Pras, Claire Forlani, Tom Waits | F44: United States | G44: 44440 | H44: Available | I44: 1999 | J44: PG-13 | K44: 121 min | L44: 121 | M44: 0 | N44: Action & Adventure | O44: A team of far-from-super heroes try to earn respect by springing into action when brave and dashing Captain Amazing disappears. | P44: Netflix | Q44: 1 | R44: =IF(G44="","",YEAR(G44)) -> 2021 | S44: =IF(G44="","",TEXT(G44,"mmmm")) -> September | T44: =IF(I44>=2020,"Recent",IF(I44>=2010,"Modern","Older")) -> Older | U44: =IF(L44=0,"Not Applicable",IF(L44< 90,"Short",IF(L44<=120,"Medium","Long"))) -> Long
A45: s8058N | B45: Movie | C45: Sons of Ben | D45: Jeffrey C. Bell | E45: Unknown | F45: United States | G45: 42714 | H45: Available | I45: 2016 | J45: Not Rated | K45: 73 min | L45: 73 | M45: 0 | N45: Documentaries | O45: Passion is an understatement. Meet the folks who wanted a Major League Soccer club in Philadelphia so badly, they became fans before it even existed. | P45: Netflix | Q45: 1 | R45: =IF(G45="","",YEAR(G45)) -> 2016 | S45: =IF(G45="","",TEXT(G45,"mmmm")) -> December | T45: =IF(I45>=2020,"Recent",IF(I45>=2010,"Modern","Older")) -> Modern | U45: =IF(L45=0,"Not Applicable",IF(L45< 90,"Short",IF(L45<=120,"Medium","Long"))) -> Short
A46: s4297P | B46: Movie | C46: Apartment 212 | D46: Haylar Garcia | E46: Penelope Mitchell, Sally Kirkland, Chris Johnson, Kyle Gass | F46: Unknown | H46: Unknown | I46: 2018 | J46: Not Rated | K46: 98 min | L46: 98 | M46: 0 | N46: Horror | O46: Jennifer is starting a new life away from an abusive ex-husband, but falls into paranoia and fear as something eats her a bite at a time as she sleeps. She must confront her fears to wage a final battle for survival before the last bite. | P46: Prime Video | Q46: 2 | R46: =IF(G46="","",YEAR(G46)) | S46: =IF(G46="","",TEXT(G46,"mmmm")) | T46: =IF(I46>=2020,"Recent",IF(I46>=2010,"Modern","Older")) -> Modern | U46: =IF(L46=0,"Not Applicable",IF(L46< 90,"Short",IF(L46<=120,"Medium","Long"))) -> Medium
A47: s9313P | B47: Movie | C47: Nanak Dukhiya Sub Sansar | D47: Dara Singh | E47: Dara Singh, Balraj Sahni, Prithviraj Kapoor, Pran, Achala Sachdev, Ram Mohan, Meena Rai | F47: Canada | H47: Unknown | I47: 1969 | J47: 13+ | K47: 132 min | L47: 132 | M47: 0 | N47: Action | O47: Two brothers, separated in the riots during the India-Pakistan separation, meet as friends. Even when they learn that they are real brothers, they do not refrain from opposing each other over a woman. | P47: Prime Video | Q47: 2 | R47: =IF(G47="","",YEAR(G47)) | S47: =IF(G47="","",TEXT(G47,"mmmm")) | T47: =IF(I47>=2020,"Recent",IF(I47>=2010,"Modern","Older")) -> Older | U47: =IF(L47=0,"Not Applicable",IF(L47< 90,"Short",IF(L47<=120,"Medium","Long"))) -> Long
A48: s5695P | B48: Movie | C48: Dead Life: Wormwood's End | D48: William Victor Schotten | E48: Unknown | F48: Unknown | H48: Unknown | I48: 2021 | J48: 16+ | K48: 80 min | L48: 80 | M48: 0 | N48: Horror | O48: Four months after the apocalypse was all it took to turn people into monsters and monsters into devils. Three survivors seek refuge with the Wormwood Militia only to find Camp Wormwood may offer protection from the walking dead - but the camp holds dangers of its own. Once the living dead begin to change into unstoppable "Necrodevils", the future begins to look hopeless. | P48: Prime Video | Q48: 2 | R48: =IF(G48="","",YEAR(G48)) | S48: =IF(G48="","",TEXT(G48,"mmmm")) | T48: =IF(I48>=2020,"Recent",IF(I48>=2010,"Modern","Older")) -> Recent | U48: =IF(L48=0,"Not Applicable",IF(L48< 90,"Short",IF(L48<=120,"Medium","Long"))) -> Short
A49: s7551N | B49: Movie | C49: My Wife and My Wifey | D49: Moataz El Tony | E49: Ramez Galal, Shery Adel, Hassan Hosny, Samy Maghawry, Youssef Eid, Raja Al-Jeddawi, Edward | F49: Unknown | G49: 43573 | H49: Available | I49: 2014 | J49: TV-14 | K49: 99 min | L49: 99 | M49: 0 | N49: Comedy | O49: A man finds his marriage to a dedicated women's rights activist facing some unexpected challenges over her commitment to the cause. | P49: Netflix | Q49: 1 | R49: =IF(G49="","",YEAR(G49)) -> 2019 | S49: =IF(G49="","",TEXT(G49,"mmmm")) -> April | T49: =IF(I49>=2020,"Recent",IF(I49>=2010,"Modern","Older")) -> Modern | U49: =IF(L49=0,"Not Applicable",IF(L49< 90,"Short",IF(L49<=120,"Medium","Long"))) -> Medium
A50: s8639P | B50: Movie | C50: Surviving The Storm | D50: Deseria Denelle | E50: Tamieka Buggage, April Grant, Shelby Wynne, Emerald Bougere | F50: Unknown | H50: Unknown | I50: 2021 | J50: 18+ | K50: 113 min | L50: 113 | M50: 0 | N50: Drama | O50: Family of women coping with generation Breast Cancer and broken relationships. | P50: Prime Video | Q50: 2 | R50: =IF(G50="","",YEAR(G50)) | S50: =IF(G50="","",TEXT(G50,"mmmm")) | T50: =IF(I50>=2020,"Recent",IF(I50>=2010,"Modern","Older")) -> Recent | U50: =IF(L50=0,"Not Applicable",IF(L50< 90,"Short",IF(L50<=120,"Medium","Long"))) -> Medium
A51: s4107P | B51: Movie | C51: Ties that Bind | D51: FrÃ©dÃ©rik D'Amours | E51: Kristanna Loken, Warren Christie, Kristen Hager, Luis Oliva, Angela Asher, Danny Blanco Hall | F51: Unknown | H51: Unknown | I51: 2010 | J51: 13+ | K51: 89 min | L51: 89 | M51: 0 | N51: Drama | O51: Hope finds herself leaving the comfort of her suburban life for New York City in order to settle the affairs of her best friend Rachel who has just been murdered. | P51: Prime Video | Q51: 2 | R51: =IF(G51="","",YEAR(G51)) | S51: =IF(G51="","",TEXT(G51,"mmmm")) | T51: =IF(I51>=2020,"Recent",IF(I51>=2010,"Modern","Older")) -> Modern | U51: =IF(L51=0,"Not Applicable",IF(L51< 90,"Short",IF(L51<=120,"Medium","Long"))) -> Short
A52: s7813N | B52: TV Show | C52: Queens of Comedy | D52: Unknown | E52: Unknown | F52: Unknown | G52: 43221 | H52: Available | I52: 2017 | J52: TV-MA | K52: 1 Season | L52: 0 | M52: 1 | N52: International TV Shows | O52: Eight women perform in front of celebrity judges and compete for the title of India’s top female stand-up comedian. | P52: Netflix | Q52: 1 | R52: =IF(G52="","",YEAR(G52)) -> 2018 | S52: =IF(G52="","",TEXT(G52,"mmmm")) -> May | T52: =IF(I52>=2020,"Recent",IF(I52>=2010,"Modern","Older")) -> Modern | U52: =IF(L52=0,"Not Applicable",IF(L52< 90,"Short",IF(L52<=120,"Medium","Long"))) -> Not Applicable
A53: s5793P | B53: Movie | C53: Razia Sultan | D53: Kamal Amrohi | E53: Dharmendra, Hema Malini, Parveen Babi, Pradeep Kumar, Vijayendra Ghatge, Ajit, Veena | F53: Unknown | H53: Unknown | I53: 1983 | J53: 13+ | K53: 151 min | L53: 151 | M53: 0 | N53: Drama | O53: Razia Sultan, the first female ruler of the Delhi Sultanate, lands in trouble and loses her kingdom when she falls in love with Jamal-ud-Din Yakut, an Abyssinian slave. | P53: Prime Video | Q53: 2 | R53: =IF(G53="","",YEAR(G53)) | S53: =IF(G53="","",TEXT(G53,"mmmm")) | T53: =IF(I53>=2020,"Recent",IF(I53>=2010,"Modern","Older")) -> Older | U53: =IF(L53=0,"Not Applicable",IF(L53< 90,"Short",IF(L53<=120,"Medium","Long"))) -> Long
A54: s1601N | B54: Movie | C54: Chico Bon Bon and the Very Berry Holiday | D54: Darragh O'Connell | E54: Robbie Daymond, Dayci Brookshire, Anthony Tedesco, Andy Abbott, Emma Sloan Jacobs, Joanna Lewis, Matt Mercer, Ian Nikus | F54: Unknown | G54: 44168 | H54: Available | I54: 2020 | J54: TV-Y | K54: 25 min | L54: 25 | M54: 0 | N54: Kids & Family Movies | O54: The Fix-It Force makes a plan to hit every home as fast as they can, delivering Blunderberry Cakes before the town awakes to avoid a holiday disaster. | P54: Netflix | Q54: 1 | R54: =IF(G54="","",YEAR(G54)) -> 2020 | S54: =IF(G54="","",TEXT(G54,"mmmm")) -> December | T54: =IF(I54>=2020,"Recent",IF(I54>=2010,"Modern","Older")) -> Recent | U54: =IF(L54=0,"Not Applicable",IF(L54< 90,"Short",IF(L54<=120,"Medium","Long"))) -> Short
A55: s7805P | B55: Movie | C55: Kidloom Songs | D55: Pipalupa Animation | E55: Kidloom | F55: Unknown | H55: Unknown | I55: 2021 | J55: ALL | K55: 47 min | L55: 47 | M55: 0 | N55: Animation | O55: Dance and sing along with all of the Kidloom characters to all sorts of fun Kids's songs- some classics and some new! Featuring Dinos, the Ecoamigos, Pipo the Astronaut Dog, Frida and more! Have fun learning about topics such as numbers, the alphabet, fruits, vegetables, animals, seasons, and emotions. | P55: Prime Video | Q55: 2 | R55: =IF(G55="","",YEAR(G55)) | S55: =IF(G55="","",TEXT(G55,"mmmm")) | T55: =IF(I55>=2020,"Recent",IF(I55>=2010,"Modern","Older")) -> Recent | U55: =IF(L55=0,"Not Applicable",IF(L55< 90,"Short",IF(L55<=120,"Medium","Long"))) -> Short
A56: s8444N | B56: Movie | C56: The One I Love | D56: Charlie McDowell | E56: Mark Duplass, Elisabeth Moss, Ted Danson | F56: United States | G56: 43615 | H56: Available | I56: 2014 | J56: R | K56: 91 min | L56: 91 | M56: 0 | N56: Comedy | O56: Confronted with the potential end of their marriage, Ethan and Sophie take off for a weekend together, hoping to negotiate their future. | P56: Netflix | Q56: 1 | R56: =IF(G56="","",YEAR(G56)) -> 2019 | S56: =IF(G56="","",TEXT(G56,"mmmm")) -> May | T56: =IF(I56>=2020,"Recent",IF(I56>=2010,"Modern","Older")) -> Modern | U56: =IF(L56=0,"Not Applicable",IF(L56< 90,"Short",IF(L56<=120,"Medium","Long"))) -> Medium
A57: s5122P | B57: TV Show | C57: Distemper | D57: Unknown | E57: Abigail Hawk, ChikÃ© Okonkwo, Tara Westwood, Matthew Conlon, Lee R. Sellars, Clare O'Malley, Lukas Hassel, Jackie Martling, Marlon Perrier | F57: Unknown | H57: Unknown | I57: 2021 | J57: TV-PG | K57: 1 Season | L57: 0 | M57: 1 | N57: TV Shows | O57: 'Distemper' tells the true story of pioneering scientist and LGBT icon Louise Pearce who races to find a cure for the African Sleeping Sickness pandemic as it rages across the Belgian Congo in the early 1920s. | P57: Prime Video | Q57: 2 | R57: =IF(G57="","",YEAR(G57)) | S57: =IF(G57="","",TEXT(G57,"mmmm")) | T57: =IF(I57>=2020,"Recent",IF(I57>=2010,"Modern","Older")) -> Recent | U57: =IF(L57=0,"Not Applicable",IF(L57< 90,"Short",IF(L57<=120,"Medium","Long"))) -> Not Applicable
A58: s1355N | B58: TV Show | C58: Heartland | D58: Unknown | E58: Amber Marshall, Michelle Morgan, Graham Wardle, Shaun Johnston, Chris Potter, Jessica Amlee, Kerry James, Nathaniel Arcand | F58: Canada | G58: 44228 | H58: Available | I58: 2019 | J58: TV-14 | K58: 13 Seasons | L58: 0 | M58: 13 | N58: Drama | O58: Spunky teenager Amy is reeling from the sudden death of her mother when she and her grandfather are threatened with the loss of their horse ranch. | P58: Netflix | Q58: 1 | R58: =IF(G58="","",YEAR(G58)) -> 2021 | S58: =IF(G58="","",TEXT(G58,"mmmm")) -> February | T58: =IF(I58>=2020,"Recent",IF(I58>=2010,"Modern","Older")) -> Modern | U58: =IF(L58=0,"Not Applicable",IF(L58< 90,"Short",IF(L58<=120,"Medium","Long"))) -> Not Applicable
A59: s7273N | B59: Movie | C59: Le K Benzema | D59: Damien Piscarel, Florent Bodin | E59: Karim Benzema | F59: France | G59: 43221 | H59: Available | I59: 2017 | J59: TV-14 | K59: 121 min | L59: 121 | M59: 0 | N59: Documentaries | O59: After a blackmailing scandal and being sidelined from the French national team, Real Madrid forward Karim Benzema tells his side of the story. | P59: Netflix | Q59: 1 | R59: =IF(G59="","",YEAR(G59)) -> 2018 | S59: =IF(G59="","",TEXT(G59,"mmmm")) -> May | T59: =IF(I59>=2020,"Recent",IF(I59>=2010,"Modern","Older")) -> Modern | U59: =IF(L59=0,"Not Applicable",IF(L59< 90,"Short",IF(L59<=120,"Medium","Long"))) -> Long
A60: s6560P | B60: Movie | C60: KevCoin: The Movie | D60: Jason Attar | E60: Jason Attar, Stella Attar, Dominic Geraghty, Martin Gooch, Yokie Lollypop, Lola-Rose Maxwell, Steve Townsend, Tony Townsend, Emilyjane Vernau | F60: Unknown | H60: Unknown | I60: 2019 | J60: 16+ | K60: 81 min | L60: 81 | M60: 0 | N60: Comedy | O60: The Worlds 1st Movie Profit Share digital currency. | P60: Prime Video | Q60: 2 | R60: =IF(G60="","",YEAR(G60)) | S60: =IF(G60="","",TEXT(G60,"mmmm")) | T60: =IF(I60>=2020,"Recent",IF(I60>=2010,"Modern","Older")) -> Modern | U60: =IF(L60=0,"Not Applicable",IF(L60< 90,"Short",IF(L60<=120,"Medium","Long"))) -> Short
A61: s3056N | B61: TV Show | C61: Cells at Work! | D61: Unknown | E61: Kana Hanazawa, Tomoaki Maeno, Daisuke Ono, Kikuko Inoue, Maria Naganawa, Takahiro Sakurai, Saori Hayami, Nobuhiko Okamoto, Yuichi Nakamura, Shoya Chiba, M・A・O, Ayako Kawasumi, Aya Endo, Hiroyuki Yoshino, Mamiko Noto | F61: Japan | G61: 43831 | H61: Available | I61: 2018 | J61: TV-PG | K61: 1 Season | L61: 0 | M61: 1 | N61: Anime Series | O61: One newcomer red blood cell just wants to do her job. Between bacteria incursions and meeting a certain white blood cell, she's got a lot to learn! | P61: Netflix | Q61: 1 | R61: =IF(G61="","",YEAR(G61)) -> 2020 | S61: =IF(G61="","",TEXT(G61,"mmmm")) -> January | T61: =IF(I61>=2020,"Recent",IF(I61>=2010,"Modern","Older")) -> Modern | U61: =IF(L61=0,"Not Applicable",IF(L61< 90,"Short",IF(L61<=120,"Medium","Long"))) -> Not Applicable
A62: s8456N | B62: Movie | C62: The Pirate Fairy | D62: Peggy Holmes | E62: Mae Whitman, Christina Hendricks, Tom Hiddleston, Lucy Liu, Raven-Symoné, Megan Hilty, Pamela Adlon, Angela Bartys, Jim Cummings, Carlos Ponce, Mick Wingert, Kevin Michael Richardson, Jeff Bennett, Rob Paulsen, Grey DeLisle, Kari Wahlgren, Jane Horrocks, Jesse McCartney, Anjelica Huston | F62: United States | G62: 41805 | H62: Available | I62: 2014 | J62: G | K62: 78 min | L62: 78 | M62: 0 | N62: Kids & Family Movies | O62: In this spritely tale, Tinker Bell and her friends set out to find free-spirited fairy Zarina after she makes off with some precious Blue Pixie Dust. | P62: Netflix | Q62: 1 | R62: =IF(G62="","",YEAR(G62)) -> 2014 | S62: =IF(G62="","",TEXT(G62,"mmmm")) -> June | T62: =IF(I62>=2020,"Recent",IF(I62>=2010,"Modern","Older")) -> Modern | U62: =IF(L62=0,"Not Applicable",IF(L62< 90,"Short",IF(L62<=120,"Medium","Long"))) -> Short
A63: s2148N | B63: Movie | C63: Diamonds in the Sky | D63: Kunle Afolayan | E63: Joke Silva, Omowunmi Dada, Bimbo Akintola, Femi Adebayo, Kayode Olaiya, Ali Nuhu, Yvonne Jegede, Toyin Abraham, Adebayo Salami, Ayo Mogaji, Magaji Mijinyawa | F63: Unknown | G63: 44051 | H63: Available | I63: 2018 | J63: TV-14 | K63: 113 min | L63: 113 | M63: 0 | N63: Drama | O63: Three families navigate uncertainty and struggle when cancer affects their lives and presents emotional challenges that test their bonds. | P63: Netflix | Q63: 1 | R63: =IF(G63="","",YEAR(G63)) -> 2020 | S63: =IF(G63="","",TEXT(G63,"mmmm")) -> August | T63: =IF(I63>=2020,"Recent",IF(I63>=2010,"Modern","Older")) -> Modern | U63: =IF(L63=0,"Not Applicable",IF(L63< 90,"Short",IF(L63<=120,"Medium","Long"))) -> Medium
A64: s6897N | B64: Movie | C64: Green Room | D64: Jeremy Saulnier | E64: Anton Yelchin, Imogen Poots, Patrick Stewart, Alia Shawkat, Joe Cole, Callum Turner, Macon Blair, David W. Thompson, Mark Webber, Eric Edelstein, Kai Lennox | F64: United States | G64: 43416 | H64: Available | I64: 2015 | J64: R | K64: 95 min | L64: 95 | M64: 0 | N64: Horror | O64: At the end of their low-budget tour, a punk band accepts a gig at an isolated rural club, only to discover that their hosts are neo-Nazis. | P64: Netflix | Q64: 1 | R64: =IF(G64="","",YEAR(G64)) -> 2018 | S64: =IF(G64="","",TEXT(G64,"mmmm")) -> November | T64: =IF(I64>=2020,"Recent",IF(I64>=2010,"Modern","Older")) -> Modern | U64: =IF(L64=0,"Not Applicable",IF(L64< 90,"Short",IF(L64<=120,"Medium","Long"))) -> Medium
A65: s5748N | B65: Movie | C65: Berserk: The Golden Age Arc I - The Egg of the King | D65: Toshiyuki Kubooka | E65: Hiroaki Iwanaga, Takahiro Sakurai, Toa Yukinari, Yuki Kaji, Minako Kotobuki, Takahiro Fujiwara, Yoshiro Matsumoto, Kazuki Yao, Aki Toyosaki, Rikiya Koyama, Kenta Miyake | F65: Japan | G65: 42658 | H65: Available | I65: 2012 | J65: TV-MA | K65: 77 min | L65: 77 | M65: 0 | N65: Action & Adventure | O65: Loner Guts is recruited by Griffith and his band of mercenaries, but their ensuing success as a full-fledged army could lead to a horrible fate. | P65: Netflix | Q65: 1 | R65: =IF(G65="","",YEAR(G65)) -> 2016 | S65: =IF(G65="","",TEXT(G65,"mmmm")) -> October | T65: =IF(I65>=2020,"Recent",IF(I65>=2010,"Modern","Older")) -> Modern | U65: =IF(L65=0,"Not Applicable",IF(L65< 90,"Short",IF(L65<=120,"Medium","Long"))) -> Short
A66: s4692N | B66: Movie | C66: Mersal | D66: Atlee Kumar | E66: Joseph Vijay, S.J. Surya, Kajal Aggarwal, Samantha Ruth Prabhu, Nithya Menon, Vadivelu, Sathyaraj | F66: India | G66: 43333 | H66: Available | I66: 2017 | J66: TV-14 | K66: 162 min | L66: 162 | M66: 0 | N66: Action & Adventure | O66: A detective arrests a doctor for crimes targeting medical professionals but later finds the real culprit in a tale of revenge, corruption and magic. | P66: Netflix | Q66: 1 | R66: =IF(G66="","",YEAR(G66)) -> 2018 | S66: =IF(G66="","",TEXT(G66,"mmmm")) -> August | T66: =IF(I66>=2020,"Recent",IF(I66>=2010,"Modern","Older")) -> Modern | U66: =IF(L66=0,"Not Applicable",IF(L66< 90,"Short",IF(L66<=120,"Medium","Long"))) -> Long
A67: s3184N | B67: TV Show | C67: The Last O.G. | D67: Unknown | E67: Tracy Morgan, Tiffany Haddish, Cedric the Entertainer, Allen Maldonado, Ryan Gaul, Taylor Mosby, Dante Hoagland, Joel Marsh Garland, Gino Vento, Derek Gaines, Daniel J. Watts, Malik Yoba, Edi Patterson | F67: United States | G67: 43803 | H67: Available | I67: 2019 | J67: TV-MA | K67: 2 Seasons | L67: 0 | M67: 2 | N67: Comedy | O67: After 15 years behind bars, a kindhearted ex-drug dealer returns to Brooklyn looking for a fresh start, only to discover things have changed. A lot. | P67: Netflix | Q67: 1 | R67: =IF(G67="","",YEAR(G67)) -> 2019 | S67: =IF(G67="","",TEXT(G67,"mmmm")) -> December | T67: =IF(I67>=2020,"Recent",IF(I67>=2010,"Modern","Older")) -> Modern | U67: =IF(L67=0,"Not Applicable",IF(L67< 90,"Short",IF(L67<=120,"Medium","Long"))) -> Not Applicable
A68: s3107N | B68: TV Show | C68: Lost in Space | D68: Unknown | E68: Molly Parker, Toby Stephens, Max Jenkins, Taylor Russell, Mina Sundwall, Parker Posey, Ignacio Serricchio | F68: United States | G68: 43823 | H68: Available | I68: 2019 | J68: TV-PG | K68: 2 Seasons | L68: 0 | M68: 2 | N68: Action & Adventure | O68: After crash-landing on an alien planet, the Robinson family fights against all odds to survive and escape. But they're surrounded by hidden dangers. | P68: Netflix | Q68: 1 | R68: =IF(G68="","",YEAR(G68)) -> 2019 | S68: =IF(G68="","",TEXT(G68,"mmmm")) -> December | T68: =IF(I68>=2020,"Recent",IF(I68>=2010,"Modern","Older")) -> Modern | U68: =IF(L68=0,"Not Applicable",IF(L68< 90,"Short",IF(L68<=120,"Medium","Long"))) -> Not Applicable
A69: s5039P | B69: Movie | C69: Prey Before You Eat | D69: Jamal Doctor | E69: Erica Graham, Yellow Diamond, Christopher Copeland | F69: Unknown | H69: Unknown | I69: 2021 | J69: 18+ | K69: 80 min | L69: 80 | M69: 0 | N69: Action | O69: A group of girls do a string of robberies, that has their lives spinning out of control. | P69: Prime Video | Q69: 2 | R69: =IF(G69="","",YEAR(G69)) | S69: =IF(G69="","",TEXT(G69,"mmmm")) | T69: =IF(I69>=2020,"Recent",IF(I69>=2010,"Modern","Older")) -> Recent | U69: =IF(L69=0,"Not Applicable",IF(L69< 90,"Short",IF(L69<=120,"Medium","Long"))) -> Short
A70: s488P | B70: Movie | C70: The Perfect Stranger | D70: Jefferson Moore, Shane Sooter | E70: Pamela Brumley, Jefferson Moore | F70: United States | H70: Unknown | I70: 2006 | J70: ALL | K70: 86 min | L70: 86 | M70: 0 | N70: Drama | O70: A cynical attorney receives a dinner invitation from a man claiming to be Jesus of Nazareth. Based on the NY Times-Bestselling novel by David Gregory. | P70: Prime Video | Q70: 2 | R70: =IF(G70="","",YEAR(G70)) | S70: =IF(G70="","",TEXT(G70,"mmmm")) | T70: =IF(I70>=2020,"Recent",IF(I70>=2010,"Modern","Older")) -> Older | U70: =IF(L70=0,"Not Applicable",IF(L70< 90,"Short",IF(L70<=120,"Medium","Long"))) -> Short
A71: s1157N | B71: Movie | C71: A Week Away | D71: Roman White | E71: Kevin Quinn, Bailee Madison, Jahbril Cook, Kat Conner Sterling, Sherri Shepherd, David Koechner, Iain Tucker, Amy Grant | F71: United States | G71: 44281 | H71: Available | I71: 2021 | J71: TV-PG | K71: 98 min | L71: 98 | M71: 0 | N71: Kids & Family Movies | O71: In this uplifting musical, a troubled teen takes a leap of faith by attending summer camp — and unexpectedly finds love, friends and a place to belong. | P71: Netflix | Q71: 1 | R71: =IF(G71="","",YEAR(G71)) -> 2021 | S71: =IF(G71="","",TEXT(G71,"mmmm")) -> March | T71: =IF(I71>=2020,"Recent",IF(I71>=2010,"Modern","Older")) -> Recent | U71: =IF(L71=0,"Not Applicable",IF(L71< 90,"Short",IF(L71<=120,"Medium","Long"))) -> Medium
A72: s4332P | B72: Movie | C72: Finding Jesus | D72: Jason Wright | E72: Unknown | F72: Unknown | H72: Unknown | I72: 2020 | J72: ALL | K72: 69 min | L72: 69 | M72: 0 | N72: Faith and Spirituality | O72: Join faith-fueled friends, Muggles and Joy, as they visit the beautiful Finding Jesus Bay, a place where Christian stories are told night and day! Guided by the sea's best storyteller, Professor Shark, they hear all about the endless kindness and boundless love of their Creator! | P72: Prime Video | Q72: 2 | R72: =IF(G72="","",YEAR(G72)) | S72: =IF(G72="","",TEXT(G72,"mmmm")) | T72: =IF(I72>=2020,"Recent",IF(I72>=2010,"Modern","Older")) -> Recent | U72: =IF(L72=0,"Not Applicable",IF(L72< 90,"Short",IF(L72<=120,"Medium","Long"))) -> Short
A73: s9247P | B73: Movie | C73: Blippi's Spooky Spells Halloween | D73: Not Available | E73: Clayton Grimm | F73: Brazil | H73: Unknown | I73: 2021 | J73: ALL | K73: 41 min | L73: 41 | M73: 0 | N73: Kids | O73: Halloween is in the air and Blippi is in the spooky spirit after finding an old, leather-bound book of "Spooky Spells." Excited to make the most of the holiday, Blippi has decked out a Halloween campfire, hopeful that these spells will offer him everything he needs to make the best Halloween ever! This episode is starring Clayton Grimm as Blippi. | P73: Prime Video | Q73: 2 | R73: =IF(G73="","",YEAR(G73)) | S73: =IF(G73="","",TEXT(G73,"mmmm")) | T73: =IF(I73>=2020,"Recent",IF(I73>=2010,"Modern","Older")) -> Recent | U73: =IF(L73=0,"Not Applicable",IF(L73< 90,"Short",IF(L73<=120,"Medium","Long"))) -> Short
A74: s1233P | B74: TV Show | C74: Quark Science | D74: Unknown | E74: Unknown | F74: Unknown | H74: Unknown | I74: 2018 | J74: 7+ | K74: 1 Season | L74: 0 | M74: 1 | N74: TV Shows | O74: Quark Science is a collection of episodes that answer some of humankind's most complicated questions: Where did we come from? What is the smallest particle? What actually drives the universe? Team up with leading scientists to uncover the answers as we know them today. The series features acclaimed British host and Professor Jim Al-Khalili, one of the world's most respected voices in science. | P74: Prime Video | Q74: 2 | R74: =IF(G74="","",YEAR(G74)) | S74: =IF(G74="","",TEXT(G74,"mmmm")) | T74: =IF(I74>=2020,"Recent",IF(I74>=2010,"Modern","Older")) -> Modern | U74: =IF(L74=0,"Not Applicable",IF(L74< 90,"Short",IF(L74<=120,"Medium","Long"))) -> Not Applicable
A75: s5111P | B75: Movie | C75: Line Walker 2: Invisible Spy | D75: Jazz Boon | E75: Louis Koo, Nick Cheung, Francis Ng | F75: Unknown | H75: Unknown | I75: 2019 | J75: 16+ | K75: 98 min | L75: 98 | M75: 0 | N75: Action | O75: An elusive hacker sparks an international war when it is revealed there may be terrorist spies embedded in the police department. Starring Louis Koo, Nick Cheung, and Francis Ng, this action packed sequel to the box office smash Line Walker, continues to explore the explosive world of heavyweight police action. | P75: Prime Video | Q75: 2 | R75: =IF(G75="","",YEAR(G75)) | S75: =IF(G75="","",TEXT(G75,"mmmm")) | T75: =IF(I75>=2020,"Recent",IF(I75>=2010,"Modern","Older")) -> Modern | U75: =IF(L75=0,"Not Applicable",IF(L75< 90,"Short",IF(L75<=120,"Medium","Long"))) -> Medium
A76: s3380N | B76: Movie | C76: Rattlesnake | D76: Zak Hilditch | E76: Carmen Ejogo, Theo Rossi, Emma Greenwell, Apollonia Pratt, Debrianna Mansini, Bruce Davis | F76: United States | G76: 43763 | H76: Available | I76: 2019 | J76: TV-MA | K76: 86 min | L76: 86 | M76: 0 | N76: Horror | O76: After a mysterious woman saves her daughter from a deadly snakebite, a single mother must repay the debt by killing a stranger before sundown. | P76: Netflix | Q76: 1 | R76: =IF(G76="","",YEAR(G76)) -> 2019 | S76: =IF(G76="","",TEXT(G76,"mmmm")) -> October | T76: =IF(I76>=2020,"Recent",IF(I76>=2010,"Modern","Older")) -> Modern | U76: =IF(L76=0,"Not Applicable",IF(L76< 90,"Short",IF(L76<=120,"Medium","Long"))) -> Short
A77: s462N | B77: Movie | C77: The Unknown Saint | D77: Alaa Eddine Aljem | E77: Younes Bouab, Salah Bensalah, Bouchaib Essamak, Mohamed Naimane, Anas Elbaz, Hassan Ben Badida, Abdelghani Kitab, Ahmed Yarziz, Rachid El Adouani, Mohamed El Moutamassik, Abdel Ghani Benizza, Adam Morjany | F77: Unknown | G77: 44392 | H77: Available | I77: 2019 | J77: TV-14 | K77: 100 min | L77: 100 | M77: 0 | N77: Comedy | O77: Following a stint behind bars, a thief returns to where he buried his loot, only to find that his hiding spot is now a shrine to an unknown saint. | P77: Netflix | Q77: 1 | R77: =IF(G77="","",YEAR(G77)) -> 2021 | S77: =IF(G77="","",TEXT(G77,"mmmm")) -> July | T77: =IF(I77>=2020,"Recent",IF(I77>=2010,"Modern","Older")) -> Modern | U77: =IF(L77=0,"Not Applicable",IF(L77< 90,"Short",IF(L77<=120,"Medium","Long"))) -> Medium
A78: s3053P | B78: Movie | C78: Black Sabbath - Paranoid (Classic Album) | D78: Matthew Longfellow | E78: Black Sabbath | F78: Unknown | H78: Unknown | I78: 2010 | J78: 16+ | K78: 55 min | L78: 55 | M78: 0 | N78: Documentaries | O78: The multi-platinum selling Paranoid is arguably Black Sabbath's finest album, not to mention one of the most seminal Heavy Metal albums of all time. This programme tells the story behind the writing, recording and success of this remarkable and groundbreaking Heavy Metal album. | P78: Prime Video | Q78: 2 | R78: =IF(G78="","",YEAR(G78)) | S78: =IF(G78="","",TEXT(G78,"mmmm")) | T78: =IF(I78>=2020,"Recent",IF(I78>=2010,"Modern","Older")) -> Modern | U78: =IF(L78=0,"Not Applicable",IF(L78< 90,"Short",IF(L78<=120,"Medium","Long"))) -> Short
A79: s5367P | B79: TV Show | C79: The Legend of Xiao Chuo | D79: Unknown | E79: Tiffany Tang, Shawn Dou, Charmaine Sheh, Jing Chao, Kevin Tan, Liu Yi Jun, Amber Lu, Jeffery Ji | F79: Unknown | H79: Unknown | I79: 2020 | J79: 13+ | K79: 1 Season | L79: 0 | M79: 1 | N79: Drama | O79: The drama tells the life of Xiao Yanyan, who was the most powerful woman of the Liao dynasty. Xiao Yanyan and Han Derang were childhood sweethearts, but were separated when she was sent into the palace to become the consort of YelÃ¼ Xian. | P79: Prime Video | Q79: 2 | R79: =IF(G79="","",YEAR(G79)) | S79: =IF(G79="","",TEXT(G79,"mmmm")) | T79: =IF(I79>=2020,"Recent",IF(I79>=2010,"Modern","Older")) -> Recent | U79: =IF(L79=0,"Not Applicable",IF(L79< 90,"Short",IF(L79<=120,"Medium","Long"))) -> Not Applicable
A80: s5074P | B80: Movie | C80: Lost in Thailand | D80: Zheng Xu | E80: Zheng Xu, Baoqiang Wang, Bo Huang | F80: Unknown | H80: Unknown | I80: 2014 | J80: 13+ | K80: 105 min | L80: 105 | M80: 0 | N80: Comedy | O80: Two rival businessmen must track down their boss at a Buddhist temple to secure a patent on a revolutionary new fuel additive. Xu catches the first plane to Bangkok, where his plans are delayed by the happy-go-lucky Wang, an unexpected travel companion who will open Xu's eyes to life's true priorities. | P80: Prime Video | Q80: 2 | R80: =IF(G80="","",YEAR(G80)) | S80: =IF(G80="","",TEXT(G80,"mmmm")) | T80: =IF(I80>=2020,"Recent",IF(I80>=2010,"Modern","Older")) -> Modern | U80: =IF(L80=0,"Not Applicable",IF(L80< 90,"Short",IF(L80<=120,"Medium","Long"))) -> Medium
A81: s6124P | B81: Movie | C81: Kansas City Confidential | D81: Phil Karlson | E81: John Payne, Coleen Gray, Preston Foster, Neville Brand, Lee Van Cleef | F81: Unknown | H81: Unknown | I81: 1952 | J81: 13+ | K81: 99 min | L81: 99 | M81: 0 | N81: Drama | O81: An ex-con trying to go straight is framed for a million-dollar armored car robbery and must go to Mexico to unmask the real culprits. | P81: Prime Video | Q81: 2 | R81: =IF(G81="","",YEAR(G81)) | S81: =IF(G81="","",TEXT(G81,"mmmm")) | T81: =IF(I81>=2020,"Recent",IF(I81>=2010,"Modern","Older")) -> Older | U81: =IF(L81=0,"Not Applicable",IF(L81< 90,"Short",IF(L81<=120,"Medium","Long"))) -> Medium
A82: s2996P | B82: Movie | C82: Boss | D82: MITCH CREDLE | E82: LASONYA OLDEN, THOMAS SYKES, TRINA ADAMS, FAHEEM SALAAM, JAYE ALLEN, STACEY TYSON, TY DICKSON, CHANTEL ROLLINS | F82: Unknown | H82: Unknown | I82: 2017 | J82: 16+ | K82: 145 min | L82: 145 | M82: 0 | N82: Action | O82: Based in Washington D.C. two childhood friends allow the love of money to become the root to their evils. Sweets, a madame of the streets comes across a truck full of drugs and instead of returning the vehicle to the notorious drug dealer, Hakeem, to which it belongs she sales the product and keeps the profit. Once Hakeem realizes Sweets is in possession of the missing truck he seeks revenge. | P82: Prime Video | Q82: 2 | R82: =IF(G82="","",YEAR(G82)) | S82: =IF(G82="","",TEXT(G82,"mmmm")) | T82: =IF(I82>=2020,"Recent",IF(I82>=2010,"Modern","Older")) -> Modern | U82: =IF(L82=0,"Not Applicable",IF(L82< 90,"Short",IF(L82<=120,"Medium","Long"))) -> Long
A83: s5383P | B83: Movie | C83: Wonder Man | D83: H. Bruce Humberstone | E83: Danny Kaye, Virginia Mayo, Vera-Ellen | F83: Unknown | H83: Unknown | I83: 1945 | J83: 13+ | K83: 98 min | L83: 98 | M83: 0 | N83: Arts | O83: After being murdered by gangsters, an exuberant nightclub entertainer returns as a ghost to persuade his meek twin brother to help bring his killers to justice. | P83: Prime Video | Q83: 2 | R83: =IF(G83="","",YEAR(G83)) | S83: =IF(G83="","",TEXT(G83,"mmmm")) | T83: =IF(I83>=2020,"Recent",IF(I83>=2010,"Modern","Older")) -> Older | U83: =IF(L83=0,"Not Applicable",IF(L83< 90,"Short",IF(L83<=120,"Medium","Long"))) -> Medium
A84: s557N | B84: Movie | C84: The 8th Night | D84: Kim Tae-hyung | E84: Lee Sung-min, Park Hae-joon, Kim You-jung, Nam Da-reum, Choi Jin-ho, Kim Dong-yeong, Lee Eal | F84: South Korea | G84: 44379 | H84: Available | I84: 2021 | J84: TV-14 | K84: 116 min | L84: 116 | M84: 0 | N84: Horror | O84: With prayer beads in one hand and an ax in the other, a monk hunts down a millennia-old spirit that's possessing humans and unleashing hell on Earth. | P84: Netflix | Q84: 1 | R84: =IF(G84="","",YEAR(G84)) -> 2021 | S84: =IF(G84="","",TEXT(G84,"mmmm")) -> July | T84: =IF(I84>=2020,"Recent",IF(I84>=2010,"Modern","Older")) -> Recent | U84: =IF(L84=0,"Not Applicable",IF(L84< 90,"Short",IF(L84<=120,"Medium","Long"))) -> Medium
A85: s3921P | B85: Movie | C85: Asuran | D85: Vetrimaaran | E85: Dhanush, Manju Warrier, Ken Karunas, Teejay Arunasalam, Pasupathy, Prakash Raj, Ammu Abirami, Balaji Sakthivel | F85: India | H85: Unknown | I85: 2019 | J85: 18+ | K85: 139 min | L85: 139 | M85: 0 | N85: Action | O85: The son of a farmer from an underprivileged caste kills a rich, upper caste landlord. Will the farmer, a loving father and a pacifist by heart, be able to save his hot-blooded son is the rest of the story. | P85: Prime Video | Q85: 2 | R85: =IF(G85="","",YEAR(G85)) | S85: =IF(G85="","",TEXT(G85,"mmmm")) | T85: =IF(I85>=2020,"Recent",IF(I85>=2010,"Modern","Older")) -> Modern | U85: =IF(L85=0,"Not Applicable",IF(L85< 90,"Short",IF(L85<=120,"Medium","Long"))) -> Long
A86: s4625P | B86: Movie | C86: Tum Bin II | D86: Anubhav Sinha | E86: Neha Sharma, Aditya Seal, Aashim Gulati, Meher Vij, Sonia Balani, Kanwaljit Singh, Jaspreet Singh, Chris Donald | F86: Unknown | H86: Unknown | I86: 2016 | J86: 13+ | K86: 141 min | L86: 141 | M86: 0 | N86: Drama | O86: Taran (Neha Sharma) finds solace in Shekhar (Aditya Seal) while coping with the untimely death of her boyfriend Amar (Aashim Gulati). Love eventually finds a way as Shekhar helps Taran get on with her life. His companionship heals her wounds and almost mends her broken heart, until fate comes knockingâ€¦ | P86: Prime Video | Q86: 2 | R86: =IF(G86="","",YEAR(G86)) | S86: =IF(G86="","",TEXT(G86,"mmmm")) | T86: =IF(I86>=2020,"Recent",IF(I86>=2010,"Modern","Older")) -> Modern | U86: =IF(L86=0,"Not Applicable",IF(L86< 90,"Short",IF(L86<=120,"Medium","Long"))) -> Long
A87: s4420N | B87: Movie | C87: They’ll Love Me When I’m Dead | D87: Morgan Neville | E87: Orson Welles, Alan Cumming | F87: United States | G87: 43406 | H87: Available | I87: 2018 | J87: TV-MA | K87: 98 min | L87: 98 | M87: 0 | N87: Documentaries | O87: Actors, crew members and others who were there discuss the tumultuous creation of Orson Welles's final, unfinished film, “The Other Side of the Wind.” | P87: Netflix | Q87: 1 | R87: =IF(G87="","",YEAR(G87)) -> 2018 | S87: =IF(G87="","",TEXT(G87,"mmmm")) -> November | T87: =IF(I87>=2020,"Recent",IF(I87>=2010,"Modern","Older")) -> Modern | U87: =IF(L87=0,"Not Applicable",IF(L87< 90,"Short",IF(L87<=120,"Medium","Long"))) -> Medium
A88: s3378P | B88: Movie | C88: A World Away | D88: Mark Blanchard | E88: Rowan Blanchard, David DeLuise, Caroline Lagerfelt, Sal Landi, Nadine Velazquez, Mary Lynn Rajskub | F88: Unknown | H88: Unknown | I88: 2019 | J88: ALL | K88: 73 min | L88: 73 | M88: 0 | N88: Kids | O88: Six kids take a trip to the Grand Canyon, but instead find themselves in a whole other world. A Dove approved production. | P88: Prime Video | Q88: 2 | R88: =IF(G88="","",YEAR(G88)) | S88: =IF(G88="","",TEXT(G88,"mmmm")) | T88: =IF(I88>=2020,"Recent",IF(I88>=2010,"Modern","Older")) -> Modern | U88: =IF(L88=0,"Not Applicable",IF(L88< 90,"Short",IF(L88<=120,"Medium","Long"))) -> Short
A89: s3576N | B89: TV Show | C89: 45 rpm | D89: Unknown | E89: Carlos Cuevas, Guiomar Puerta, Iván Marcos, Israel Elejalde, Eudald Font, Luis Larrodera, Carmen Gutiérrez, Diana Gómez, Vito Sanz, Marina San José, Pere Ponce, Joan Pera | F89: Spain | G89: 43693 | H89: Available | I89: 2019 | J89: TV-MA | K89: 1 Season | L89: 0 | M89: 1 | N89: International TV Shows | O89: In 1960s Madrid, music producer Guillermo Rojas launches a rock 'n' roll label with the help of aspiring singer Robert and clever producer Maribel. | P89: Netflix | Q89: 1 | R89: =IF(G89="","",YEAR(G89)) -> 2019 | S89: =IF(G89="","",TEXT(G89,"mmmm")) -> August | T89: =IF(I89>=2020,"Recent",IF(I89>=2010,"Modern","Older")) -> Modern | U89: =IF(L89=0,"Not Applicable",IF(L89< 90,"Short",IF(L89<=120,"Medium","Long"))) -> Not Applicable
A90: s1385P | B90: Movie | C90: Panther's Claw | D90: William Beaudine | E90: Sidney Blackmer, Byron Foulger, Gerta Rozan, Joaquin Edwards, Herbert Rawlinson, Frank Darien | F90: Unknown | H90: Unknown | I90: 1942 | J90: 18+ | K90: 78 min | L90: 78 | M90: 0 | N90: Suspense | O90: Mild-mannered Everett P. Digberry is found wandering in a cemetary by police and arested for loitering. Digberry protests, claiming he was supposed to meet a man known only as the Black Panther, who had been blackmailing him. But the paw print on the blackmail note belongs to Blackberry's own cat. Then, opera singer Nina Politza (Rozan) is found murdered, and Digberry, her lover, is the prime suspect. However, commissioner Thatcher Colt (Blackmer) doubts Digberry committed the crime, due to a large number of other suspects with better motives for murder. Rival wigmaker Samuel Wilkins is killed and the murder weapon planted in Digberry's apartment. Commissioner Colt must clear Digberry's name and find the real murderer before someone else is killed. | P90: Prime Video | Q90: 2 | R90: =IF(G90="","",YEAR(G90)) | S90: =IF(G90="","",TEXT(G90,"mmmm")) | T90: =IF(I90>=2020,"Recent",IF(I90>=2010,"Modern","Older")) -> Older | U90: =IF(L90=0,"Not Applicable",IF(L90< 90,"Short",IF(L90<=120,"Medium","Long"))) -> Short
A91: s3147P | B91: TV Show | C91: Barney | D91: Unknown | E91: Dean Wendt, Carey Stinson, Julie Johnson, Lauren Mayeux, Patty Wirtz | F91: Unknown | H91: Unknown | I91: 2009 | J91: TV-Y | K91: 10 Seasons | L91: 0 | M91: 10 | N91: Kids | O91: Travel the world with Barney and his friends! The search is on for colorful eggs in Kenya, a music box in Switzerland, birds of paradise in Hawaii, and a dancing horse in Spain. Baby Bop brings her butterfly Monty to Mexico, while Barney introduces Rusty to China. And everyone puts on a show in Greece. Sing along to your favorite songs on this worldwide adventure with Barney and his friends. | P91: Prime Video | Q91: 2 | R91: =IF(G91="","",YEAR(G91)) | S91: =IF(G91="","",TEXT(G91,"mmmm")) | T91: =IF(I91>=2020,"Recent",IF(I91>=2010,"Modern","Older")) -> Older | U91: =IF(L91=0,"Not Applicable",IF(L91< 90,"Short",IF(L91<=120,"Medium","Long"))) -> Not Applicable
A92: s631N | B92: Movie | C92: Killing Them Softly | D92: Andrew Dominik | E92: Brad Pitt, Scoot McNairy, Ben Mendelsohn, Richard Jenkins, James Gandolfini, Ray Liotta, Vincent Curatola, Slaine, Max Casella, Trevor Long, Sam Shepard | F92: United States | G92: 44375 | H92: Available | I92: 2012 | J92: R | K92: 97 min | L92: 97 | M92: 0 | N92: Drama | O92: When a couple of low-level crooks rob a Mob-protected poker game, a slick enforcer is hired to track down the offenders and take care of business. | P92: Netflix | Q92: 1 | R92: =IF(G92="","",YEAR(G92)) -> 2021 | S92: =IF(G92="","",TEXT(G92,"mmmm")) -> June | T92: =IF(I92>=2020,"Recent",IF(I92>=2010,"Modern","Older")) -> Modern | U92: =IF(L92=0,"Not Applicable",IF(L92< 90,"Short",IF(L92<=120,"Medium","Long"))) -> Medium
A93: s2743N | B93: TV Show | C93: Sunderland 'Til I Die | D93: Unknown | E93: Unknown | F93: United Kingdom | G93: 43922 | H93: Available | I93: 2020 | J93: TV-MA | K93: 2 Seasons | L93: 0 | M93: 2 | N93: British TV Shows | O93: This docuseries follows English soccer club Sunderland through the 2017-18 season as they try to bounce back after relegation from the Premier League. | P93: Netflix | Q93: 1 | R93: =IF(G93="","",YEAR(G93)) -> 2020 | S93: =IF(G93="","",TEXT(G93,"mmmm")) -> April | T93: =IF(I93>=2020,"Recent",IF(I93>=2010,"Modern","Older")) -> Recent | U93: =IF(L93=0,"Not Applicable",IF(L93< 90,"Short",IF(L93<=120,"Medium","Long"))) -> Not Applicable
A94: s5983P | B94: Movie | C94: Delaware Shore | D94: Raghav Peri | E94: Francis, Portsmith, Ed Aristone, Emily McKinley Hill | F94: Unknown | H94: Unknown | I94: 2018 | J94: 18+ | K94: 98 min | L94: 98 | M94: 0 | N94: Drama | O94: A Holocaust survivor who escapes the concentration camps finds refuge on a secluded Delaware Beach and raises her abandoned twin grandKids. | P94: Prime Video | Q94: 2 | R94: =IF(G94="","",YEAR(G94)) | S94: =IF(G94="","",TEXT(G94,"mmmm")) | T94: =IF(I94>=2020,"Recent",IF(I94>=2010,"Modern","Older")) -> Modern | U94: =IF(L94=0,"Not Applicable",IF(L94< 90,"Short",IF(L94<=120,"Medium","Long"))) -> Medium
A95: s2809N | B95: TV Show | C95: We Speak Dance | D95: Unknown | E95: Vandana Hart | F95: United States | G95: 43907 | H95: Available | I95: 2018 | J95: TV-MA | K95: 1 Season | L95: 0 | M95: 1 | N95: Docuseries | O95: Trained dancer Vandana Hart travels the world to learn traditional and urban dance styles from the local experts who know them best. | P95: Netflix | Q95: 1 | R95: =IF(G95="","",YEAR(G95)) -> 2020 | S95: =IF(G95="","",TEXT(G95,"mmmm")) -> March | T95: =IF(I95>=2020,"Recent",IF(I95>=2010,"Modern","Older")) -> Modern | U95: =IF(L95=0,"Not Applicable",IF(L95< 90,"Short",IF(L95<=120,"Medium","Long"))) -> Not Applicable
A96: s9414P | B96: Movie | C96: Us | D96: Michael Landon | E96: Michael Landon, Barney Martin, Casey Peterson | F96: Dubai | H96: Unknown | I96: 1991 | J96: 16+ | K96: 94 min | L96: 94 | M96: 0 | N96: Drama | O96: In his final role, Michael Landon plays a man trying to reunite his family when, after eighteen years behind bars, he is proven innocent. Co-starring David Speilberg and Barney Martin. | P96: Prime Video | Q96: 2 | R96: =IF(G96="","",YEAR(G96)) | S96: =IF(G96="","",TEXT(G96,"mmmm")) | T96: =IF(I96>=2020,"Recent",IF(I96>=2010,"Modern","Older")) -> Older | U96: =IF(L96=0,"Not Applicable",IF(L96< 90,"Short",IF(L96<=120,"Medium","Long"))) -> Medium
A97: s8333N | B97: Movie | C97: The Great Gambler | D97: Shakti Samanta | E97: Amitabh Bachchan, Zeenat Aman, Neetu Singh, Prem Chopra, Utpal Dutt, Madan Puri, Om Shivpuri, Iftekhar, Sujit Kumar, Roopesh Kumar | F97: India | G97: 43830 | H97: Available | I97: 1979 | J97: TV-14 | K97: 161 min | L97: 161 | M97: 0 | N97: Action & Adventure | O97: After unwittingly using his skills to obtain military secrets, a gambler is pursued by a police officer who happens to be his doppelgänger. | P97: Netflix | Q97: 1 | R97: =IF(G97="","",YEAR(G97)) -> 2019 | S97: =IF(G97="","",TEXT(G97,"mmmm")) -> December | T97: =IF(I97>=2020,"Recent",IF(I97>=2010,"Modern","Older")) -> Older | U97: =IF(L97=0,"Not Applicable",IF(L97< 90,"Short",IF(L97<=120,"Medium","Long"))) -> Long
A98: s7939P | B98: Movie | C98: The Aggression Scale | D98: Steven C. Miller | E98: Ray Wise, Dana Ashbrook, Derek Mears, Ryan Hartwig, Fabianne Therese | F98: Unknown | H98: Unknown | I98: 2012 | J98: R | K98: 85 min | L98: 85 | M98: 0 | N98: Action | O98: Four heavily armed hitmen and two unusual teenagers go to war over $500,000 of stolen cash. | P98: Prime Video | Q98: 2 | R98: =IF(G98="","",YEAR(G98)) | S98: =IF(G98="","",TEXT(G98,"mmmm")) | T98: =IF(I98>=2020,"Recent",IF(I98>=2010,"Modern","Older")) -> Modern | U98: =IF(L98=0,"Not Applicable",IF(L98< 90,"Short",IF(L98<=120,"Medium","Long"))) -> Short
A99: s9391P | B99: Movie | C99: Code Red | D99: Valeri Milev | E99: Paul Logan, Manal El-Feitury, Mya-Lecia Naylor, Julian Kostov | F99: Costa Rica | H99: Unknown | I99: 2014 | J99: 16+ | K99: 94 min | L99: 94 | M99: 0 | N99: Action | O99: A Special Forces soldier is sent into Bulgaria when a chemical agent from WWII is uncovered that can reanimate the dead. | P99: Prime Video | Q99: 2 | R99: =IF(G99="","",YEAR(G99)) | S99: =IF(G99="","",TEXT(G99,"mmmm")) | T99: =IF(I99>=2020,"Recent",IF(I99>=2010,"Modern","Older")) -> Modern | U99: =IF(L99=0,"Not Applicable",IF(L99< 90,"Short",IF(L99<=120,"Medium","Long"))) -> Medium
A100: s2475N | B100: Movie | C100: One Day We'll Talk About Today | D100: Angga Dwimas Sasongko | E100: Rachel Amanda, Rio Dewanto, Shelia Dara, Donny Damara, Susan Bachtiar, Oka Antara, Niken Anjani, Ardhito Pramono | F100: Indonesia | G100: 43974 | H100: Available | I100: 2020 | J100: TV-G | K100: 128 min | L100: 128 | M100: 0 | N100: Drama | O100: Harboring a deep secret, a seemingly happy family confronts the trauma of years past as a clash between generations threatens to separate them. | P100: Netflix | Q100: 1 | R100: =IF(G100="","",YEAR(G100)) -> 2020 | S100: =IF(G100="","",TEXT(G100,"mmmm")) -> May | T100: =IF(I100>=2020,"Recent",IF(I100>=2010,"Modern","Older")) -> Recent | U100: =IF(L100=0,"Not Applicable",IF(L100< 90,"Short",IF(L100<=120,"Medium","Long"))) -> Long
...

Sheet Content_Overview
A1: OTT Content Overview
A2: Netflix vs Prime Video - Content Composition and key metrices
A4: PLATFORM OVERVIEW | F4: CONTENT MIX
A5: METRIC | B5: Netflix | C5: prime video | D5: Total | F5: Content Type | G5: Percentage
A6: Total Content | B6: =COUNTIF(OTT_Data!P:P,"Netflix") -> 1431 | C6: =COUNTIF(OTT_Data!P:P,"Prime Video") -> 1569 | D6: =SUM(B6,C6) -> 3000 | F6: Movies | G6: =D7/Table2[[#This Row],[Total]] -> 0.75466667
A7: Movies | B7: =COUNTIFS(OTT_Data!P:P,"Netflix",OTT_Data!B:B,"Movie") -> 996 | C7: =COUNTIFS(OTT_Data!P:P,"Prime Video",OTT_Data!B:B,"Movie") -> 1268 | D7: =SUM(B7,C7) -> 2264 | F7: TV Shows | G7: =D8/D6 -> 0.24533333
A8: TV Shows | B8: =COUNTIFS(OTT_Data!P:P,"Netflix",OTT_Data!B:B,"TV Show") -> 435 | C8: =COUNTIFS(OTT_Data!P:P,"Prime Video",OTT_Data!B:B,"TV Show") -> 301 | D8: =SUM(B8:C8) -> 736
A10: RATING ANALYSIS
A11: Rating | B11: Netflix | C11: Prime Video | D11: Total | F11: PLATFORM CONTENT COMPOSITION
A12: 16+ | B12: =COUNTIFS(OTT_Data!$P:$P,"Netflix",OTT_Data!$J:$J,A12) -> 0 | C12: =COUNTIFS(OTT_Data!$P:$P,"Prime Video",OTT_Data!$J:$J,A12) -> 258 | D12: =SUM(B12:C12) -> 258 | F12: Content Type | G12: Netflix % | H12: Prime Video%
A13: 18+ | B13: =COUNTIFS(OTT_Data!$P:$P,"Netflix",OTT_Data!$J:$J,A13) -> 0 | C13: =COUNTIFS(OTT_Data!$P:$P,"Prime Video",OTT_Data!$J:$J,A13) -> 216 | D13: =SUM(B13:C13) -> 216 | F13: Movies | G13: =B7/B6 -> 0.69601677 | H13: =C7/C6 -> 0.80815806
A14: 13+ | B14: =COUNTIFS(OTT_Data!$P:$P,"Netflix",OTT_Data!$J:$J,A14) -> 0 | C14: =COUNTIFS(OTT_Data!$P:$P,"Prime Video",OTT_Data!$J:$J,A14) -> 350 | D14: =SUM(B14:C14) -> 350 | F14: TV Shows | G14: =B8/B6 -> 0.30398323 | H14: =C8/C6 -> 0.19184194
A15: TV-14 | B15: =COUNTIFS(OTT_Data!$P:$P,"Netflix",OTT_Data!$J:$J,A15) -> 351 | C15: =COUNTIFS(OTT_Data!$P:$P,"Prime Video",OTT_Data!$J:$J,A15) -> 42 | D15: =SUM(B15:C15) -> 393 | F15: Total | G15: =SUM(G13:G14) -> 1 | H15: =SUM(H13:H14) -> 1
A16: TV-MA | B16: =COUNTIFS(OTT_Data!$P:$P,"Netflix",OTT_Data!$J:$J,A16) -> 518 | C16: =COUNTIFS(OTT_Data!$P:$P,"Prime Video",OTT_Data!$J:$J,A16) -> 8 | D16: =SUM(B16:C16) -> 526
A17: PG-13 | B17: =COUNTIFS(OTT_Data!$P:$P,"Netflix",OTT_Data!$J:$J,A17) -> 101 | C17: =COUNTIFS(OTT_Data!$P:$P,"Prime Video",OTT_Data!$J:$J,A17) -> 56 | D17: =SUM(B17:C17) -> 157
A18: PG | B18: =COUNTIFS(OTT_Data!$P:$P,"Netflix",OTT_Data!$J:$J,A18) -> 51 | C18: =COUNTIFS(OTT_Data!$P:$P,"Prime Video",OTT_Data!$J:$J,A18) -> 33 | D18: =SUM(B18:C18) -> 84 | F18: KEY PLATFORM METRICS
A19: TV-PG | B19: =COUNTIFS(OTT_Data!$P:$P,"Netflix",OTT_Data!$J:$J,A19) -> 136 | C19: =COUNTIFS(OTT_Data!$P:$P,"Prime Video",OTT_Data!$J:$J,A19) -> 33 | D19: =SUM(B19:C19) -> 169 | F19: Total Titles | G19: 3000
A20: TV-G | B20: =COUNTIFS(OTT_Data!$P:$P,"Netflix",OTT_Data!$J:$J,A20) -> 36 | C20: =COUNTIFS(OTT_Data!$P:$P,"Prime Video",OTT_Data!$J:$J,A20) -> 13 | D20: =SUM(B20:C20) -> 49 | F20: Netflix Titles | G20: =B6 -> 1431
A21: G | B21: =COUNTIFS(OTT_Data!$P:$P,"Netflix",OTT_Data!$J:$J,A21) -> 2 | C21: =COUNTIFS(OTT_Data!$P:$P,"Prime Video",OTT_Data!$J:$J,A21) -> 19 | D21: =SUM(B21:C21) -> 21 | F21: Prime Video Titles | G21: =C6 -> 1569
A22: Not Rated | B22: =COUNTIFS(OTT_Data!$P:$P,"Netflix",OTT_Data!$J:$J,A22) -> 18 | C22: =COUNTIFS(OTT_Data!$P:$P,"Prime Video",OTT_Data!$J:$J,A22) -> 96 | D22: =SUM(B22:C22) -> 114 | F22: Total Movies | G22: =D7 -> 2264
F23: Total TV Shows | G23: =D8 -> 736
F24: Average Movie Duration | G24: =D27 -> 95.04115
A25: AVERAGE DURATION ANALYSIS
A26: Metric | B26: Netflix | C26: Prime Video | D26: Overall
A27: Average Movie Duration | B27: =AVERAGEIFS(OTT_Data!$L:$L,OTT_Data!$P:$P,"Netflix",OTT_Data!$L:$L,">0") -> 100.94975 | C27: =AVERAGEIFS(OTT_Data!$L:$L,OTT_Data!$P:$P,"Prime Video",OTT_Data!$L:$L,">0") -> 90.393676 | D27: =AVERAGEIF(OTT_Data!$L:$L,">0",OTT_Data!$L:$L) -> 95.04115 | F27: Netflix vs Prime Video — Content Type | K27: Average Movie Duration
A28: Short Movies | B28: =COUNTIFS(OTT_Data!$P:$P,"Netflix",OTT_Data!$U:$U,"Short") -> 274 | C28: =COUNTIFS(OTT_Data!$P:$P,"Prime Video",OTT_Data!$U:$U,"Short") -> 583 | D28: =SUM(B28:C28) -> 857
A29: Medium Movies | B29: =COUNTIFS(OTT_Data!$P:$P,"Netflix",OTT_Data!$U:$U,"Medium") -> 508 | C29: =COUNTIFS(OTT_Data!$P:$P,"Prime Video",OTT_Data!$U:$U,"Medium") -> 517 | D29: =SUM(B29:C29) -> 1025
A30: Long Movies | B30: =COUNTIFS(OTT_Data!$P:$P,"Netflix",OTT_Data!$U:$U,"Long") -> 213 | C30: =COUNTIFS(OTT_Data!$P:$P,"Prime Video",OTT_Data!$U:$U,"Long") -> 165 | D30: =SUM(B30:C30) -> 378
G46: Rating Distribution by Platform

Sheet Content_Trends
A1: OTT CONTENT TRENDS
A2: Year-wise analysis of content added across Netflix and Prime Video
A4: CONTENT ADDED BY YEAR | F4: Netflix Content Added by Year
A6: Year | B6: Netflix | C6: Total
A7: 2011 | B7: =COUNTIFS(OTT_Data!$R:$R,$A5,OTT_Data!$P:$P,"Netflix") -> 0 | C7: =SUM(B7:B7) -> 0
A8: 2013 | B8: =COUNTIFS(OTT_Data!$R:$R,$A6,OTT_Data!$P:$P,"Netflix") -> 0 | C8: =SUM(B8:B8) -> 0
A9: 2014 | B9: =COUNTIFS(OTT_Data!$R:$R,$A7,OTT_Data!$P:$P,"Netflix") -> 2 | C9: =SUM(B9:B9) -> 2
A10: 2015 | B10: =COUNTIFS(OTT_Data!$R:$R,$A8,OTT_Data!$P:$P,"Netflix") -> 3 | C10: =SUM(B10:B10) -> 3
A11: 2016 | B11: =COUNTIFS(OTT_Data!$R:$R,$A9,OTT_Data!$P:$P,"Netflix") -> 8 | C11: =SUM(B11:B11) -> 8
A12: 2017 | B12: =COUNTIFS(OTT_Data!$R:$R,$A10,OTT_Data!$P:$P,"Netflix") -> 11 | C12: =SUM(B12:B12) -> 11
A13: 2018 | B13: =COUNTIFS(OTT_Data!$R:$R,$A11,OTT_Data!$P:$P,"Netflix") -> 78 | C13: =SUM(B13:B13) -> 78
A14: 2019 | B14: =COUNTIFS(OTT_Data!$R:$R,$A12,OTT_Data!$P:$P,"Netflix") -> 171 | C14: =SUM(B14:B14) -> 171
A15: 2020 | B15: =COUNTIFS(OTT_Data!$R:$R,$A13,OTT_Data!$P:$P,"Netflix") -> 255 | C15: =SUM(B15:B15) -> 255
A16: 2021 | B16: =COUNTIFS(OTT_Data!$R:$R,$A14,OTT_Data!$P:$P,"Netflix") -> 334 | C16: =SUM(B16:B16) -> 334
A17: 2024 | B17: =COUNTIFS(OTT_Data!$R:$R,$A15,OTT_Data!$P:$P,"Netflix") -> 309 | C17: =SUM(B17:B17) -> 309
A19: DATE AVAILABILITY
A21: Metric | B21: Counts
A22: Total Netflix Titles | B22: =COUNTIF(OTT_Data!P:P,"Netflix") -> 1431 | F22: Availability of Added Year Data
A23: Netflix with Added Year | B23: =COUNTIFS(OTT_Data!P:P,"Netflix",OTT_Data!R:R,">0") -> 1429
A24: Netflix without Added Year | B24: =B22-B23 -> 2
A25: Total Prime Video Titles | B25: =COUNTIF(OTT_Data!P:P,"Prime Video") -> 1569
A26: Prime Video with Added Year | B26: =COUNTIFS(OTT_Data!P:P,"Prime Video",OTT_Data!R:R,">0") -> 17
A27: Prime Video without Added Year | B27: =B25-B26 -> 1552

Sheet content_country_genre_analysis
A1: OTT CONTENT ANALYSIS
A2: Movie, TV Show, Duration and Content Age Analysis
A4: CONTENT TYPE ANALYSIS | F4: Movies vs TV Shows by Platform | O4: Movie Duration Category Comparison | X4: Content Age Distribution by Platform
A5: Content Type | B5: Netflix | C5: Prime Video | D5: Total
A6: Movies | B6: =COUNTIFS(OTT_Data!$P:$P,"Netflix",OTT_Data!$B:$B,"Movie") -> 996 | C6: =COUNTIFS(OTT_Data!$P:$P,"Prime Video",OTT_Data!$B:$B,"Movie") -> 1268 | D6: =SUM(B6:C6) -> 2264
A7: TV Shows | B7: =COUNTIFS(OTT_Data!$P:$P,"Netflix",OTT_Data!$B:$B,"TV Show") -> 435 | C7: =COUNTIFS(OTT_Data!$P:$P,"Prime Video",OTT_Data!$B:$B,"TV Show") -> 301 | D7: =SUM(B7:C7) -> 736
A10: MOVIE DURATION ANALYSIS
A11: Metric | B11: Netflix | C11: Prime Video | D11: Overall
A12: Average Movie Duration | B12: =AVERAGEIFS(OTT_Data!$L:$L,OTT_Data!$P:$P,"Netflix",OTT_Data!$B:$B,"Movie") -> 100.84839 | C12: =AVERAGEIFS(OTT_Data!$L:$L,OTT_Data!$P:$P,"Prime Video",OTT_Data!$B:$B,"Movie") -> 90.179811 | D12: =AVERAGEIFS(OTT_Data!$L:$L,OTT_Data!$B:$B,"Movie") -> 94.873233
A13: Short Movies | B13: =COUNTIFS(OTT_Data!$P:$P,"Netflix",OTT_Data!$U:$U,"Short") -> 274 | C13: =COUNTIFS(OTT_Data!$P:$P,"Prime Video",OTT_Data!$U:$U,"Short") -> 583 | D13: =SUM(B13:C13) -> 857
A14: Medium Movies | B14: =COUNTIFS(OTT_Data!$P:$P,"Netflix",OTT_Data!$U:$U,"Medium") -> 508 | C14: =COUNTIFS(OTT_Data!$P:$P,"Prime Video",OTT_Data!$U:$U,"Medium") -> 517 | D14: =SUM(B14:C14) -> 1025
A15: Long Movies | B15: =COUNTIFS(OTT_Data!$P:$P,"Netflix",OTT_Data!$U:$U,"Long") -> 213 | C15: =COUNTIFS(OTT_Data!$P:$P,"Prime Video",OTT_Data!$U:$U,"Long") -> 165 | D15: =SUM(B15:C15) -> 378
A17: CONTENT AGE ANALYSIS
A18: Metric | B18: Netflix | C18: Prime Video | D18: Overall
A19: Recent | B19: =COUNTIFS(OTT_Data!$P:$P,"Netflix",OTT_Data!$T:$T,"Recent") -> 264 | C19: =COUNTIFS(OTT_Data!$P:$P,"Prime Video",OTT_Data!$T:$T,"Recent") -> 407 | D19: =SUM(B19:C19) -> 671
A20: Modern | B20: =COUNTIFS(OTT_Data!$P:$P,"Netflix",OTT_Data!$T:$T,"Modern") -> 937 | C20: =COUNTIFS(OTT_Data!$P:$P,"Prime Video",OTT_Data!$T:$T,"Modern") -> 692 | D20: =SUM(B20:C20) -> 1629
A21: Older | B21: =COUNTIFS(OTT_Data!$P:$P,"Netflix",OTT_Data!$T:$T,"Older") -> 230 | C21: =COUNTIFS(OTT_Data!$P:$P,"Prime Video",OTT_Data!$T:$T,"Older") -> 470 | D21: =SUM(B21:C21) -> 700
A24: OTT COUNTRY ANALYSIS
A25: COUNTRY-WISE CONTENT DISTRIBUTION ACROSS NETFLIX AND PRIME VIDEO | K25: Country-wise OTT Content Distribution | S25: Netflix vs Prime Video — Country Comparison
A27: Country | B27: Total Titles
A28: United States | B28: =COUNTIF(OTT_Data!$F:$F,"*"&A28&"*") -> 748
A29: India | B29: =COUNTIF(OTT_Data!$F:$F,"*"&A29&"*") -> 216
A30: United Kingdom | B30: =COUNTIF(OTT_Data!$F:$F,"*"&A30&"*") -> 167
A31: France | B31: =COUNTIF(OTT_Data!$F:$F,"*"&A31&"*") -> 79
A32: Canada | B32: =COUNTIF(OTT_Data!$F:$F,"*"&A32&"*") -> 67
A33: Japan | B33: =COUNTIF(OTT_Data!$F:$F,"*"&A33&"*") -> 60
A34: Germany | B34: =COUNTIF(OTT_Data!$F:$F,"*"&A34&"*") -> 50
A35: Spain | B35: =COUNTIF(OTT_Data!$F:$F,"*"&A35&"*") -> 44
A36: Australia | B36: =COUNTIF(OTT_Data!$F:$F,"*"&A36&"*") -> 35
A37: Mexico | B37: =COUNTIF(OTT_Data!$F:$F,"*"&A37&"*") -> 26
A39: NETFLIX VS PRIME VIDEO — COUNTRY COMPARISON
A40: Country | B40: Netflix | C40: Prime Video
A41: United States | B41: =COUNTIFS(OTT_Data!$F:$F,"*"&A41&"*",OTT_Data!$P:$P,"Netflix") -> 629 | C41: =COUNTIFS(OTT_Data!$F:$F,"*"&A41&"*",OTT_Data!$P:$P,"Prime Video") -> 119
A42: India | B42: =COUNTIFS(OTT_Data!$F:$F,"*"&A42&"*",OTT_Data!$P:$P,"Netflix") -> 172 | C42: =COUNTIFS(OTT_Data!$F:$F,"*"&A42&"*",OTT_Data!$P:$P,"Prime Video") -> 44
A43: United Kingdom | B43: =COUNTIFS(OTT_Data!$F:$F,"*"&A43&"*",OTT_Data!$P:$P,"Netflix") -> 134 | C43: =COUNTIFS(OTT_Data!$F:$F,"*"&A43&"*",OTT_Data!$P:$P,"Prime Video") -> 33
A44: France | B44: =COUNTIFS(OTT_Data!$F:$F,"*"&A44&"*",OTT_Data!$P:$P,"Netflix") -> 74 | C44: =COUNTIFS(OTT_Data!$F:$F,"*"&A44&"*",OTT_Data!$P:$P,"Prime Video") -> 5
A45: Canada | B45: =COUNTIFS(OTT_Data!$F:$F,"*"&A45&"*",OTT_Data!$P:$P,"Netflix") -> 56 | C45: =COUNTIFS(OTT_Data!$F:$F,"*"&A45&"*",OTT_Data!$P:$P,"Prime Video") -> 11
A46: Japan | B46: =COUNTIFS(OTT_Data!$F:$F,"*"&A46&"*",OTT_Data!$P:$P,"Netflix") -> 53 | C46: =COUNTIFS(OTT_Data!$F:$F,"*"&A46&"*",OTT_Data!$P:$P,"Prime Video") -> 7
A47: Germany | B47: =COUNTIFS(OTT_Data!$F:$F,"*"&A47&"*",OTT_Data!$P:$P,"Netflix") -> 46 | C47: =COUNTIFS(OTT_Data!$F:$F,"*"&A47&"*",OTT_Data!$P:$P,"Prime Video") -> 4
A48: Spain | B48: =COUNTIFS(OTT_Data!$F:$F,"*"&A48&"*",OTT_Data!$P:$P,"Netflix") -> 39 | C48: =COUNTIFS(OTT_Data!$F:$F,"*"&A48&"*",OTT_Data!$P:$P,"Prime Video") -> 5
A49: Australia | B49: =COUNTIFS(OTT_Data!$F:$F,"*"&A49&"*",OTT_Data!$P:$P,"Netflix") -> 28 | C49: =COUNTIFS(OTT_Data!$F:$F,"*"&A49&"*",OTT_Data!$P:$P,"Prime Video") -> 7
A50: Mexico | B50: =COUNTIFS(OTT_Data!$F:$F,"*"&A50&"*",OTT_Data!$P:$P,"Netflix") -> 23 | C50: =COUNTIFS(OTT_Data!$F:$F,"*"&A50&"*",OTT_Data!$P:$P,"Prime Video") -> 3
A53: OTT GENRE ANALYSIS
A54: Genre Distribution and Platform-wise Content Comparison | I54: Genre Lookup using INDEX + MATCH
A56: Genre | B56: Netflix | C56: Prime Video | D56: Total | I56: Genre | J56: Netflix | K56: Prime Video | L56: Total | V56: Genre | W56: Total
A57: Drama | B57: =COUNTIFS(OTT_Data!$N:$N,"*"&A57&"*",OTT_Data!$P:$P,"Netflix") -> 303 | C57: =COUNTIFS(OTT_Data!$N:$N,"*"&A57&"*",OTT_Data!$P:$P,"Prime Video") -> 353 | D57: =SUM(B57:C57) -> 656 | I57: comedy | J57: =INDEX($B$57:$B$66,MATCH(I57,$A$57:$A$66,0)) -> 295 | K57: =INDEX($C$57:$C$66,MATCH(I57,$A$57:$A$66,0)) -> 238 | L57: =INDEX($D$57:$D$66,MATCH(I57,$A$57:$A$66,0)) -> 533 | V57: Drama | W57: 656
A58: Comedy | B58: =COUNTIFS(OTT_Data!$N:$N,"*"&A58&"*",OTT_Data!$P:$P,"Netflix") -> 295 | C58: =COUNTIFS(OTT_Data!$N:$N,"*"&A58&"*",OTT_Data!$P:$P,"Prime Video") -> 238 | D58: =SUM(B58:C58) -> 533 | V58: Comedy | W58: 533
A59: Action | B59: =COUNTIFS(OTT_Data!$N:$N,"*"&A59&"*",OTT_Data!$P:$P,"Netflix") -> 155 | C59: =COUNTIFS(OTT_Data!$N:$N,"*"&A59&"*",OTT_Data!$P:$P,"Prime Video") -> 266 | D59: =SUM(B59:C59) -> 421 | V59: Action | W59: 421
A60: Documentary | B60: =COUNTIFS(OTT_Data!$N:$N,"*"&A60&"*",OTT_Data!$P:$P,"Netflix") -> 8 | C60: =COUNTIFS(OTT_Data!$N:$N,"*"&A60&"*",OTT_Data!$P:$P,"Prime Video") -> 42 | D60: =SUM(B60:C60) -> 50 | V60: Documentary | W60: 50
A61: Thriller | B61: =COUNTIFS(OTT_Data!$N:$N,"*"&A61&"*",OTT_Data!$P:$P,"Netflix") -> 16 | C61: =COUNTIFS(OTT_Data!$N:$N,"*"&A61&"*",OTT_Data!$P:$P,"Prime Video") -> 0 | D61: =SUM(B61:C61) -> 16 | V61: Thriller | W61: 16
A62: Romance | B62: =COUNTIFS(OTT_Data!$N:$N,"*"&A62&"*",OTT_Data!$P:$P,"Netflix") -> 5 | C62: =COUNTIFS(OTT_Data!$N:$N,"*"&A62&"*",OTT_Data!$P:$P,"Prime Video") -> 17 | D62: =SUM(B62:C62) -> 22 | V62: Romance | W62: 22
A63: Horror | B63: =COUNTIFS(OTT_Data!$N:$N,"*"&A63&"*",OTT_Data!$P:$P,"Netflix") -> 50 | C63: =COUNTIFS(OTT_Data!$N:$N,"*"&A63&"*",OTT_Data!$P:$P,"Prime Video") -> 87 | D63: =SUM(B63:C63) -> 137 | V63: Horror | W63: 137
A64: Family | B64: =COUNTIFS(OTT_Data!$N:$N,"*"&A64&"*",OTT_Data!$P:$P,"Netflix") -> 86 | C64: =COUNTIFS(OTT_Data!$N:$N,"*"&A64&"*",OTT_Data!$P:$P,"Prime Video") -> 0 | D64: =SUM(B64:C64) -> 86 | V64: Family | W64: 86
A65: Crime | B65: =COUNTIFS(OTT_Data!$N:$N,"*"&A65&"*",OTT_Data!$P:$P,"Netflix") -> 50 | C65: =COUNTIFS(OTT_Data!$N:$N,"*"&A65&"*",OTT_Data!$P:$P,"Prime Video") -> 0 | D65: =SUM(B65:C65) -> 50 | V65: Crime | W65: 50
A66: Animation | B66: =COUNTIFS(OTT_Data!$N:$N,"*"&A66&"*",OTT_Data!$P:$P,"Netflix") -> 0 | C66: =COUNTIFS(OTT_Data!$N:$N,"*"&A66&"*",OTT_Data!$P:$P,"Prime Video") -> 95 | D66: =SUM(B66:C66) -> 95 | V66: Animation | W66: 95
A69: Genre-wise OTT Content Distribution | J69: Netflix vs Prime Video Genre Comparison

Sheet pivot_table_analysis
A1: OTT Pivot Table Analysis
A3: Pivot 1:Platform-wise Content | E3: Pivot 2:Platform vs Genre | I3: Pivot 3:Year-wise Content
A4: Row Labels | B4: Count of type | C4: Count of show_id | E4: Count of title | F4: Column Labels | I4: Row Labels | J4: Count of title
A5: Prime Video | B5: 17 | C5: 17 | E5: Row Labels | F5: Prime Video | G5: Grand Total | I5: 1947 | J5: 1
A6: Grand Total | B6: 17 | C6: 17 | E6: Action | F6: 8 | G6: 8 | I6: 1955 | J6: 1
E7: Drama | F7: 7 | G7: 7 | I7: 1964 | J7: 1
E8: Romance | F8: 1 | G8: 1 | I8: 1973 | J8: 1
A9: Pivot 4:Genre-wise Content | E9: Young Adult Audience | F9: 1 | G9: 1 | I9: 1995 | J9: 1
A10: Row Labels | B10: Count of title | E10: Grand Total | F10: 17 | G10: 17 | I10: 2003 | J10: 1
A11: Action | B11: 8 | I11: 2007 | J11: 1
A12: Drama | B12: 7 | I12: 2011 | J12: 1
A13: Romance | B13: 1 | I13: 2015 | J13: 1
A14: Young Adult Audience | B14: 1 | I14: 2016 | J14: 1
A15: Grand Total | B15: 17 | I15: 2018 | J15: 1
I16: 2019 | J16: 2
I17: 2021 | J17: 4
I18: Grand Total | J18: 17
E61: Pivot 5:Movies vs TV Shows
E62: Row Labels | F62: Count of title
E63: Movie | F63: 13
E64: TV Show | F64: 4
E65: Grand Total | F65: 17

Sheet ott_dashboard
A1: OTT CONTENT ANALYSIS DASHBOARD
A5: Platform Distribution | D5: Movies vs TV Shows | I5: Genre-wise OTT Content Distribution | M5: Netflix vs Prime Video by Genre

Sheet Summary
A1: KEY INSIGHTS / SUMMARY
A3: Insight | B3: Finding
A4: Total Content | B4: 3,000 titles are available across both OTT platforms.
A5: Platform Leader | B5: Prime Video has 1,569 titles, slightly more than Netflix's 1,431.
A6: Content Type | B6: Movies dominate with 2,264 titles, while TV Shows have 736.
A7: Top Genre | B7: Drama is the largest genre with 656 titles.
A8: Second Largest Genre | B8: Comedy has 470 titles.
A9: Action Content | B9: Action has 266 titles.
A10: Content Growth | B10: Content increases significantly from 2014 onward, with 2020–2021 having the highest yearly counts in your data.
A11: Platform Comparison | B11: Prime Video has more total titles than Netflix, but the distribution varies by genre.
